<?xml version="1.0" encoding="utf-8"?>
<Window>
	<Form Height="704" Id="form" Left="8" OnLoadCompleted="CSTSKN01500_OnLoadCompleted" PidAttrib="7" Title="판매등급등록(skn)" Top="8" Ver="1.0" Width="1040" WorkArea="true">
		<Datasets>
			<Dataset DataSetType="Dataset" Id="ds_rdoPower">
				<Contents>
					<colinfo id="code" size="256" summ="default" type="STRING"/>
					<colinfo id="value" size="256" summ="default" type="STRING"/>
					<record>
						<code>111</code>
						<value>이상없음</value>
					</record>
					<record>
						<code>411</code>
						<value>간헐적불량</value>
					</record>
					<record>
						<code>513</code>
						<value>전원안켜짐</value>
					</record>
					<record>
						<code>523</code>
						<value>반복적&#32;불량으로&#32;사용불가</value>
					</record>
				</Contents>
			</Dataset>
			<Dataset DataSetType="Dataset" Id="ds_rdoUsim">
				<Contents>
					<colinfo id="code" size="256" summ="default" type="STRING"/>
					<colinfo id="value" size="256" summ="default" type="STRING"/>
					<record>
						<code>111</code>
						<value>이상없음</value>
					</record>
					<record>
						<code>411</code>
						<value>간헐적&#32;USIM&#32;불량</value>
					</record>
					<record>
						<code>513</code>
						<value>안테나&#32;표시&#32;불가</value>
					</record>
					<record>
						<code>523</code>
						<value>USIM장착&#32;불가</value>
					</record>
					<record>
						<code>533</code>
						<value>타유심제한</value>
					</record>
				</Contents>
			</Dataset>
			<Dataset DataSetType="Dataset" Id="ds_rdoCharge">
				<Contents>
					<colinfo id="code" size="256" summ="default" type="STRING"/>
					<colinfo id="value" size="256" summ="default" type="STRING"/>
					<record>
						<code>111</code>
						<value>이상없음</value>
					</record>
					<record>
						<code>411</code>
						<value>간헐적&#32;불량</value>
					</record>
					<record>
						<code>513</code>
						<value>충전불가</value>
					</record>
					<record>
						<code>523</code>
						<value>지속적&#32;불량으로&#32;사용불가</value>
					</record>
				</Contents>
			</Dataset>
			<Dataset DataSetType="Dataset" Id="ds_rdoBell">
				<Contents>
					<colinfo id="code" size="256" summ="default" type="STRING"/>
					<colinfo id="value" size="256" summ="default" type="STRING"/>
					<record>
						<code>111</code>
						<value>이상없음</value>
					</record>
					<record>
						<code>311</code>
						<value>볼륨작음/잡음섞임</value>
					</record>
					<record>
						<code>411</code>
						<value>볼륨&#32;조절&#32;불가</value>
					</record>
					<record>
						<code>423</code>
						<value>출력불가</value>
					</record>
				</Contents>
			</Dataset>
			<Dataset DataSetType="Dataset" Id="ds_rdoVibration">
				<Contents>
					<colinfo id="code" size="256" summ="default" type="STRING"/>
					<colinfo id="value" size="256" summ="default" type="STRING"/>
					<record>
						<code>111</code>
						<value>이상없음</value>
					</record>
					<record>
						<code>311</code>
						<value>진동약함/간헐적불량</value>
					</record>
					<record>
						<code>413</code>
						<value>진동안됨</value>
					</record>
				</Contents>
			</Dataset>
			<Dataset DataSetType="Dataset" Id="ds_rdoCpnt">
				<Contents>
					<colinfo id="code" size="256" summ="default" type="STRING"/>
					<colinfo id="value" size="256" summ="default" type="STRING"/>
					<record>
						<code>111</code>
						<value>이상없음</value>
					</record>
					<record>
						<code>513</code>
						<value>구성품&#32;없음</value>
					</record>
				</Contents>
			</Dataset>
			<Dataset DataSetType="Dataset" Id="ds_rdoJodo">
				<Contents>
					<colinfo id="code" size="256" summ="default" type="STRING"/>
					<colinfo id="value" size="256" summ="default" type="STRING"/>
					<record>
						<code>111</code>
						<value>이상없음</value>
					</record>
					<record>
						<code>311</code>
						<value>작동불가</value>
					</record>
				</Contents>
			</Dataset>
			<Dataset DataSetType="Dataset" Id="ds_rdoGyro">
				<Contents>
					<colinfo id="code" size="256" summ="default" type="STRING"/>
					<colinfo id="value" size="256" summ="default" type="STRING"/>
					<record>
						<code>111</code>
						<value>이상없음</value>
					</record>
					<record>
						<code>411</code>
						<value>작동불가</value>
					</record>
				</Contents>
			</Dataset>
			<Dataset DataSetType="Dataset" Id="ds_rdoProximity">
				<Contents>
					<colinfo id="code" size="256" summ="default" type="STRING"/>
					<colinfo id="value" size="256" summ="default" type="STRING"/>
					<record>
						<code>111</code>
						<value>이상없음</value>
					</record>
					<record>
						<code>411</code>
						<value>작동불가</value>
					</record>
				</Contents>
			</Dataset>
			<Dataset DataSetType="Dataset" Id="ds_rdoCamera">
				<Contents>
					<colinfo id="code" size="256" summ="default" type="STRING"/>
					<colinfo id="value" size="256" summ="default" type="STRING"/>
					<record>
						<code>111</code>
						<value>이상없음</value>
					</record>
					<record>
						<code>421</code>
						<value>카메라&#32;흑점/렌즈마모/초점&#32;안맞음</value>
					</record>
					<record>
						<code>413</code>
						<value>구동불가</value>
					</record>
				</Contents>
			</Dataset>
			<Dataset DataSetType="Dataset" Id="ds_rdoBattery">
				<Contents>
					<colinfo id="code" size="256" summ="default" type="STRING"/>
					<colinfo id="value" size="256" summ="default" type="STRING"/>
					<record>
						<code>111</code>
						<value>이상없음</value>
					</record>
					<record>
						<code>311</code>
						<value>B/T불량</value>
					</record>
				</Contents>
			</Dataset>
			<Dataset DataSetType="Dataset" Id="ds_rdoAfterimage">
				<Contents>
					<colinfo id="code" size="256" summ="default" type="STRING"/>
					<colinfo id="value" size="256" summ="default" type="STRING"/>
					<record>
						<code>111</code>
						<value>이상없음</value>
					</record>
					<record>
						<code>311</code>
						<value>약잔상(TEST모드)</value>
					</record>
					<record>
						<code>321</code>
						<value>중잔상(TEST&#32;모드)</value>
					</record>
					<record>
						<code>513</code>
						<value>강잔상(바탕화면&#32;잔상)</value>
					</record>
				</Contents>
			</Dataset>
			<Dataset DataSetType="Dataset" Id="ds_rdoTouch">
				<Contents>
					<colinfo id="code" size="256" summ="default" type="STRING"/>
					<colinfo id="value" size="256" summ="default" type="STRING"/>
					<record>
						<code>111</code>
						<value>이상없음</value>
					</record>
					<record>
						<code>413</code>
						<value>Test&#32;모드&#32;터치불가</value>
					</record>
					<record>
						<code>423</code>
						<value>부분터치&#32;불가</value>
					</record>
					<record>
						<code>513</code>
						<value>전체터치&#32;불가</value>
					</record>
				</Contents>
			</Dataset>
			<Dataset DataSetType="Dataset" Id="ds_rdoWifi">
				<Contents>
					<colinfo id="code" size="256" summ="default" type="STRING"/>
					<colinfo id="value" size="256" summ="default" type="STRING"/>
					<record>
						<code>111</code>
						<value>이상없음</value>
					</record>
					<record>
						<code>411</code>
						<value>WIFI불량</value>
					</record>
				</Contents>
			</Dataset>
			<Dataset DataSetType="Dataset" Id="ds_rdoStain">
				<Contents>
					<colinfo id="code" size="256" summ="default" type="STRING"/>
					<colinfo id="value" size="256" summ="default" type="STRING"/>
					<record>
						<code>111</code>
						<value>이상없음</value>
					</record>
					<record>
						<code>413</code>
						<value>얼룩&#32;존재(20%&#32;이상)</value>
					</record>
				</Contents>
			</Dataset>
			<Dataset DataSetType="Dataset" Id="ds_rdoBruise">
				<Contents>
					<colinfo id="code" size="256" summ="default" type="STRING"/>
					<colinfo id="value" size="256" summ="default" type="STRING"/>
					<record>
						<code>111</code>
						<value>이상없음</value>
					</record>
					<record>
						<code>413</code>
						<value>멍&#32;존재(20%&#32;이상)</value>
					</record>
				</Contents>
			</Dataset>
			<Dataset DataSetType="Dataset" Id="ds_rdoSquash">
				<Contents>
					<colinfo id="code" size="256" summ="default" type="STRING"/>
					<colinfo id="value" size="256" summ="default" type="STRING"/>
					<record>
						<code>111</code>
						<value>이상없음</value>
					</record>
					<record>
						<code>311</code>
						<value>눌림있음</value>
					</record>
				</Contents>
			</Dataset>
			<Dataset DataSetType="Dataset" Id="ds_rdoLiquefied">
				<Contents>
					<colinfo id="code" size="256" summ="default" type="STRING"/>
					<colinfo id="value" size="256" summ="default" type="STRING"/>
					<record>
						<code>111</code>
						<value>이상없음</value>
					</record>
					<record>
						<code>413</code>
						<value>액상유입&#32;존재(20%&#32;이상)</value>
					</record>
				</Contents>
			</Dataset>
			<Dataset DataSetType="Dataset" Id="ds_rdoLed">
				<Contents>
					<colinfo id="code" size="256" summ="default" type="STRING"/>
					<colinfo id="value" size="256" summ="default" type="STRING"/>
					<record>
						<code>111</code>
						<value>이상없음</value>
					</record>
					<record>
						<code>513</code>
						<value>내부회로물&#32;보임&#32;</value>
					</record>
					<record>
						<code>523</code>
						<value>줄감&#32;및&#32;안나옴</value>
					</record>
				</Contents>
			</Dataset>
			<Dataset DataSetType="Dataset" Id="ds_rdoButton">
				<Contents>
					<colinfo id="code" size="256" summ="default" type="STRING"/>
					<colinfo id="value" size="256" summ="default" type="STRING"/>
					<record>
						<code>111</code>
						<value>이상없음</value>
					</record>
					<record>
						<code>311</code>
						<value>눌림감&#32;약함</value>
					</record>
					<record>
						<code>411</code>
						<value>간헐적&#32;작동&#32;불가&#32;or&#32;일부&#32;파손(기능이상&#32;없음)</value>
					</record>
					<record>
						<code>513</code>
						<value>완전&#32;작동&#32;불가&#32;or&#32;전체&#32;파손(기능이상있음)</value>
					</record>
				</Contents>
			</Dataset>
			<Dataset DataSetType="Dataset" Id="ds_rdoBottom">
				<Contents>
					<colinfo id="code" size="256" summ="default" type="STRING"/>
					<colinfo id="value" size="256" summ="default" type="STRING"/>
					<record>
						<code>111</code>
						<value>이상없음</value>
					</record>
					<record>
						<code>311</code>
						<value>조명불량/터치불량</value>
					</record>
				</Contents>
			</Dataset>
			<Dataset DataSetType="Dataset" Id="ds_rdoBody">
				<Contents>
					<colinfo id="code" size="256" summ="default" type="STRING"/>
					<colinfo id="value" size="256" summ="default" type="STRING"/>
					<record>
						<code>111</code>
						<value>이상없음</value>
					</record>
					<record>
						<code>311</code>
						<value>휨&#32;존재</value>
					</record>
				</Contents>
			</Dataset>
			<Dataset DataSetType="Dataset" Id="ds_rdoDmb">
				<Contents>
					<colinfo id="code" size="256" summ="default" type="STRING"/>
					<colinfo id="value" size="256" summ="default" type="STRING"/>
					<record>
						<code>111</code>
						<value>이상없음</value>
					</record>
					<record>
						<code>311</code>
						<value>손상/벗겨짐/missing</value>
					</record>
				</Contents>
			</Dataset>
			<Dataset DataSetType="Dataset" Id="ds_rdoGlass">
				<Contents>
					<colinfo id="code" size="256" summ="default" type="STRING"/>
					<colinfo id="value" size="256" summ="default" type="STRING"/>
					<record>
						<code>111</code>
						<value>이상없음</value>
					</record>
					<record>
						<code>411</code>
						<value>균열존재(판넬손)</value>
					</record>
				</Contents>
			</Dataset>
			<Dataset DataSetType="Dataset" Id="ds_rdoTeeth">
				<Contents>
					<colinfo id="code" size="256" summ="default" type="STRING"/>
					<colinfo id="value" size="256" summ="default" type="STRING"/>
					<record>
						<code>111</code>
						<value>이상없음</value>
					</record>
					<record>
						<code>311</code>
						<value>SIDE&#32;존재</value>
					</record>
					<record>
						<code>411</code>
						<value>전면부&#32;존재</value>
					</record>
				</Contents>
			</Dataset>
			<Dataset DataSetType="Dataset" Id="ds_rdoWindow">
				<Contents>
					<colinfo id="code" size="256" summ="default" type="STRING"/>
					<colinfo id="value" size="256" summ="default" type="STRING"/>
					<record>
						<code>111</code>
						<value>이상없음</value>
					</record>
					<record>
						<code>311</code>
						<value>SIDE&#32;존재</value>
					</record>
					<record>
						<code>411</code>
						<value>전면부&#32;존재</value>
					</record>
				</Contents>
			</Dataset>
			<Dataset DataSetType="Dataset" Id="ds_rdoEdge">
				<Contents>
					<colinfo id="code" size="256" summ="default" type="STRING"/>
					<colinfo id="value" size="256" summ="default" type="STRING"/>
					<record>
						<code>111</code>
						<value>이상없음</value>
					</record>
					<record>
						<code>211</code>
						<value>긁힘,&#32;찍힘,&#32;도색벗겨짐&#32;존재</value>
					</record>
					<record>
						<code>311</code>
						<value>균열&#32;존재(A0외&#32;상태)</value>
					</record>
					<record>
						<code>411</code>
						<value>파손(떨어져&#32;나감)</value>
					</record>
				</Contents>
			</Dataset>
			<Dataset DataSetType="Dataset" Id="ds_rdoReturn">
				<Contents>
					<colinfo id="code" size="256" summ="default" type="STRING"/>
					<colinfo id="value" size="256" summ="default" type="STRING"/>
					<record>
						<code>61</code>
						<value>패턴잠김</value>
					</record>
					<record>
						<code>62</code>
						<value>Icloud&#32;잠김</value>
					</record>
					<record>
						<code>63</code>
						<value>IMEI&#32;확인불가</value>
					</record>
					<record>
						<code>64</code>
						<value>분실/도난</value>
					</record>
				</Contents>
			</Dataset>
			<Dataset DataSetType="Dataset" Id="ds_saleEqpSt">
				<Contents>
					<colinfo id="PROD_CD" size="256" summ="default" type="STRING"/>
					<colinfo id="COLOR_CD" size="256" summ="default" type="STRING"/>
					<colinfo id="SER_NUM" size="256" summ="default" type="STRING"/>
					<colinfo id="CON_MGMT_NO" size="256" summ="default" type="STRING"/>
					<colinfo id="POWER_ST" size="256" summ="default" type="STRING"/>
					<colinfo id="USIM_ST" size="256" summ="default" type="STRING"/>
					<colinfo id="CHARGE_ST" size="256" summ="default" type="STRING"/>
					<colinfo id="BELL_ST" size="256" summ="default" type="STRING"/>
					<colinfo id="VIBRATION_ST" size="256" summ="default" type="STRING"/>
					<colinfo id="CPNT_ST" size="256" summ="default" type="STRING"/>
					<colinfo id="JODO_ST" size="256" summ="default" type="STRING"/>
					<colinfo id="GYRO_ST" size="256" summ="default" type="STRING"/>
					<colinfo id="PROXIMITY_ST" size="256" summ="default" type="STRING"/>
					<colinfo id="CAMERA_ST" size="256" summ="default" type="STRING"/>
					<colinfo id="BATTERY_ST" size="256" summ="default" type="STRING"/>
					<colinfo id="AFTERIMAGE_ST" size="256" summ="default" type="STRING"/>
					<colinfo id="TOUCH_ST" size="256" summ="default" type="STRING"/>
					<colinfo id="WIFI_ST" size="256" summ="default" type="STRING"/>
					<colinfo id="STAIN_ST" size="256" summ="default" type="STRING"/>
					<colinfo id="BRUISE_ST" size="256" summ="default" type="STRING"/>
					<colinfo id="SQUASH_ST" size="256" summ="default" type="STRING"/>
					<colinfo id="LIQUEFIED_ST" size="256" summ="default" type="STRING"/>
					<colinfo id="LED_ST" size="256" summ="default" type="STRING"/>
					<colinfo id="BUTTON_ST" size="256" summ="default" type="STRING"/>
					<colinfo id="BOTTOM_ST" size="256" summ="default" type="STRING"/>
					<colinfo id="BODY_ST" size="256" summ="default" type="STRING"/>
					<colinfo id="DMB_ST" size="256" summ="default" type="STRING"/>
					<colinfo id="GLASS_ST" size="256" summ="default" type="STRING"/>
					<colinfo id="TEETH_ST" size="256" summ="default" type="STRING"/>
					<colinfo id="WINDOW_ST" size="256" summ="default" type="STRING"/>
					<colinfo id="EDGE_ST" size="256" summ="default" type="STRING"/>
					<colinfo id="RETURN_ST" size="256" summ="default" type="STRING"/>
					<colinfo id="SALE_EQP_ST" size="256" summ="default" type="STRING"/>
					<colinfo id="RETURN_CL" size="256" summ="default" type="STRING"/>
					<colinfo id="EQP_ST" size="256" summ="default" type="STRING"/>
					<record>
						<AFTERIMAGE_ST></AFTERIMAGE_ST>
						<BATTERY_ST></BATTERY_ST>
						<BELL_ST></BELL_ST>
						<BODY_ST></BODY_ST>
						<BOTTOM_ST></BOTTOM_ST>
						<BRUISE_ST></BRUISE_ST>
						<BUTTON_ST></BUTTON_ST>
						<CAMERA_ST></CAMERA_ST>
						<CHARGE_ST></CHARGE_ST>
						<COLOR_CD></COLOR_CD>
						<CON_MGMT_NO></CON_MGMT_NO>
						<CPNT_ST></CPNT_ST>
						<DMB_ST></DMB_ST>
						<EDGE_ST></EDGE_ST>
						<EQP_ST></EQP_ST>
						<GLASS_ST></GLASS_ST>
						<GYRO_ST></GYRO_ST>
						<JODO_ST></JODO_ST>
						<LED_ST></LED_ST>
						<LIQUEFIED_ST></LIQUEFIED_ST>
						<POWER_ST></POWER_ST>
						<PROD_CD></PROD_CD>
						<PROXIMITY_ST></PROXIMITY_ST>
						<RETURN_CL></RETURN_CL>
						<RETURN_ST></RETURN_ST>
						<SALE_EQP_ST></SALE_EQP_ST>
						<SER_NUM></SER_NUM>
						<SQUASH_ST></SQUASH_ST>
						<STAIN_ST></STAIN_ST>
						<TEETH_ST></TEETH_ST>
						<TOUCH_ST></TOUCH_ST>
						<USIM_ST></USIM_ST>
						<VIBRATION_ST></VIBRATION_ST>
						<WIFI_ST></WIFI_ST>
						<WINDOW_ST></WINDOW_ST>
					</record>
				</Contents>
			</Dataset>
		</Datasets>
		<Image Align="Left" Height="24" Id="Image2" ImageID="bul_tit" Left="6" LeftMargin="15" OnClick="Image2_OnClick" Style="sty_img_tit" TabOrder="1" Text="판매등급&#32;검수" Top="49" Width="114"></Image>
		<Div Border="Raised" Height="41" Id="div_conInfo8" Left="8" Style="sty_div_search" TabOrder="2" Text="질의내용" Top="8" Width="1008">
			<Contents>
				<Static Align="Right" Height="20" Id="Static3" Left="17" Style="sty_lb_Search" TabOrder="1" Text="접수관리번호" Top="9" VAlign="Middle" Width="85"></Static>
				<Edit BindDataset="ds_saleEqpSt" Border="Flat" Column="CON_MGMT_NO" Enable="FALSE" Height="20" Id="edt_conMgmtNo" Left="110" MaxLength="15" OnKeyDown="div_conInfo8_edt_conMgmtNo_OnKeyDown" Style="sty_ipt_form" TabOrder="1" Top="8" UpperOnly="TRUE" Width="133"></Edit>
				<Static Align="Right" Height="29" Id="Static2" Left="534" Style="sty_lb_Search" TabOrder="3" Text="판매등급" Top="3" VAlign="Middle" Width="72"></Static>
				<Edit Align="CENTER" BindDataset="ds_saleEqpSt" Border="Flat" Column="SALE_EQP_ST" Enable="FALSE" Height="20" Id="edt_saleEqpSt" Left="614" MaxLength="15" Style="sty_ipt_form" TabOrder="4" Top="7" UpperOnly="TRUE" Width="69"></Edit>
				<Static Align="Right" Height="29" Id="Static0" Left="366" Style="sty_lb_Search" TabOrder="5" Text="매입등급" Top="3" VAlign="Middle" Width="72"></Static>
				<Edit Align="CENTER" BindDataset="ds_saleEqpSt" Border="Flat" Column="EQP_ST" Enable="FALSE" Height="20" Id="edt_eqpSt" Left="446" MaxLength="15" Style="sty_ipt_form" TabOrder="6" Top="8" UpperOnly="TRUE" Width="69"></Edit>
				<Static Color="user27" Height="20" Id="sta_joinWay" Left="254" Style="sty_lb_Basic" TabOrder="7" Top="9" VAlign="Middle" Width="53"></Static>
			</Contents>
		</Div>
		<Div Border="Raised" Height="40" Id="Div0" Left="6" Style="sty_div_search" TabOrder="3" Text="질의내용" Top="71" Width="56">
			<Contents></Contents>
		</Div>
		<Div Border="Raised" Height="148" Id="Div1" Left="6" Style="sty_div_search" TabOrder="4" Text="질의내용" Top="108" Width="56">
			<Contents>
				<Static Align="Right" Height="82" Id="Static4" Left="7" Style="sty_lb_Search" TabOrder="1" Text="기본점검" Top="22" VAlign="Middle" Width="32" WordWrap="TRUE"></Static>
			</Contents>
		</Div>
		<Div Border="Raised" Height="40" Id="Div2" Left="59" Style="sty_div_search" TabOrder="5" Text="질의내용" Top="71" Width="150">
			<Contents>
				<Static Align="Center" Height="21" Id="Static4" Left="8" Style="sty_lb_Search" TabOrder="1" Text="주요&#32;증상" Top="7" VAlign="Middle" Width="131"></Static>
			</Contents>
		</Div>
		<Div Border="Raised" Height="67" Id="div_choice1" Left="206" Style="sty_div_search" TabOrder="6" Text="질의내용" Top="108" Width="333">
			<Contents>
				<Radio BindDataset="ds_saleEqpSt" Border="None" CodeColumn="code" Column="POWER_ST" ColumnCount="2" DataColumn="value" Height="50" Id="rdo_power" INDEX="-1" InnerDataset="ds_rdoPower" Left="3" LeftMargin="5" OnChanged="f_st_set" RightMargin="19" Style="sty_opt_search" TabOrder="1" Top="6" Value="N" Width="320">
					<Contents>
						<Layout code="Y" height="20" left="10" text="Y" top="0" width="30"/>
						<Layout code="N" height="20" left="60" text="N" top="0" width="30"/>
					</Contents>
				</Radio>
			</Contents>
		</Div>
		<Div Border="Raised" Height="40" Id="Div5" Left="206" Style="sty_div_search" TabOrder="7" Text="질의내용" Top="71" Width="333">
			<Contents>
				<Static Align="Center" Height="21" Id="Static4" Left="3" Style="sty_lb_Search" TabOrder="1" Text="점검&#32;사항" Top="6" VAlign="Middle" Width="320"></Static>
			</Contents>
		</Div>
		<Div Border="Raised" Height="67" Id="Div6" Left="59" Style="sty_div_search" TabOrder="8" Text="질의내용" Top="108" Width="150">
			<Contents>
				<Static Align="Center" Height="40" Id="Static0" Left="7" TabOrder="1" Text="전원&#32;불량" Top="12" VAlign="Middle" Width="132" WordWrap="TRUE"></Static>
			</Contents>
		</Div>
		<Div Border="Raised" Height="40" Id="Div7" Left="536" Style="sty_div_search" TabOrder="9" Text="질의내용" Top="71" Width="150">
			<Contents>
				<Static Align="Center" Height="21" Id="Static4" Left="8" Style="sty_lb_Search" TabOrder="1" Text="주요&#32;증상" Top="7" VAlign="Middle" Width="131"></Static>
			</Contents>
		</Div>
		<Div Border="Raised" Height="67" Id="Div8" Left="536" Style="sty_div_search" TabOrder="10" Text="질의내용" Top="108" Width="150">
			<Contents>
				<Static Align="Center" Height="40" Id="Static0" Left="6" TabOrder="1" Text="충전&#32;불량" Top="12" VAlign="Middle" Width="139" WordWrap="TRUE"></Static>
			</Contents>
		</Div>
		<Div Border="Raised" Height="84" Id="div_choice3" Left="206" Style="sty_div_search" TabOrder="11" Text="질의내용" Top="172" Width="333">
			<Contents>
				<Radio BindDataset="ds_saleEqpSt" Border="None" CodeColumn="code" Column="USIM_ST" ColumnCount="2" DataColumn="value" Height="68" Id="rdo_usim" INDEX="-1" InnerDataset="ds_rdoUsim" Left="3" LeftMargin="5" OnChanged="f_st_set" RightMargin="61" Style="sty_opt_search" TabOrder="1" Top="4" Value="N" Width="320">
					<Contents>
						<Layout code="Y" height="20" left="10" text="Y" top="0" width="30"/>
						<Layout code="N" height="20" left="60" text="N" top="0" width="30"/>
					</Contents>
				</Radio>
			</Contents>
		</Div>
		<Div Border="Raised" Height="84" Id="Div10" Left="59" Style="sty_div_search" TabOrder="11" Text="질의내용" Top="172" Width="150">
			<Contents>
				<Static Align="Center" Height="40" Id="Static0" Left="5" TabOrder="1" Text="USIM&#32;불량" Top="19" VAlign="Middle" Width="132" WordWrap="TRUE"></Static>
			</Contents>
		</Div>
		<Div Border="Raised" Height="195" Id="Div3" Left="6" Style="sty_div_search" TabOrder="11" Text="질의내용" Top="572" Width="56">
			<Contents>
				<Static Align="Right" Height="82" Id="Static4" Left="6" Style="sty_lb_Search" TabOrder="1" Text="화면&#13;&#10;점검" Top="57" VAlign="Middle" Width="32" WordWrap="TRUE"></Static>
			</Contents>
		</Div>
		<Div Border="Raised" Height="40" Id="Div92" Left="683" Style="sty_div_search" TabOrder="14" Text="질의내용" Top="71" Width="333">
			<Contents>
				<Static Align="Center" Height="21" Id="Static4" Left="3" Style="sty_lb_Search" TabOrder="1" Text="점검&#32;사항" Top="6" VAlign="Middle" Width="320"></Static>
			</Contents>
		</Div>
		<Button Align="Left" ButtonStyle="TRUE" Cursor="HAND" Height="25" Id="btn_save" ImageID="btn_c_2" Left="877" LeftMargin="5" OnClick="btn_save_OnClick" Style="sty_btn_c" TabOrder="15" Text="저장" Top="1110" Width="60"></Button>
		<Button Align="Left" ButtonStyle="TRUE" Height="24" Id="btn_close" ImageID="btn_d_2" Left="944" LeftMargin="5" OnClick="btn_close_OnClick" Style="sty_btn_d" TabOrder="16" Text="닫기" Top="1110" Width="61"></Button>
		<Div Border="Raised" Height="67" Id="div_choice2" Left="683" Style="sty_div_search" TabOrder="17" Text="질의내용" Top="108" Width="333">
			<Contents>
				<Radio BindDataset="ds_saleEqpSt" Border="None" CodeColumn="code" Column="CHARGE_ST" ColumnCount="2" DataColumn="value" Height="50" Id="rdo_charge" INDEX="-1" InnerDataset="ds_rdoCharge" Left="3" LeftMargin="5" OnChanged="f_st_set" RightMargin="25" Style="sty_opt_search" TabOrder="1" Top="6" Value="N" Width="320">
					<Contents>
						<Layout code="Y" height="20" left="10" text="Y" top="0" width="30"/>
						<Layout code="N" height="20" left="60" text="N" top="0" width="30"/>
					</Contents>
				</Radio>
			</Contents>
		</Div>
		<Div Border="Raised" Height="323" Id="Div12" Left="6" Style="sty_div_search" TabOrder="18" Text="질의내용" Top="252" Width="56">
			<Contents>
				<Static Align="Right" Height="82" Id="Static4" Left="9" Style="sty_lb_Search" TabOrder="1" Text="기능&#13;&#10;점검" Top="145" VAlign="Middle" Width="32" WordWrap="TRUE"></Static>
			</Contents>
		</Div>
		<Div Border="Raised" Height="67" Id="div_choice4" Left="206" Style="sty_div_search" TabOrder="19" Text="질의내용" Top="252" Width="333">
			<Contents>
				<Radio BindDataset="ds_saleEqpSt" Border="None" CodeColumn="code" Column="BELL_ST" ColumnCount="2" DataColumn="value" Height="50" Id="rdo_bell" INDEX="-1" InnerDataset="ds_rdobell" Left="3" LeftMargin="5" OnChanged="f_st_set" RightMargin="58" Style="sty_opt_search" TabOrder="1" Top="6" Value="N" Width="320">
					<Contents>
						<Layout code="Y" height="20" left="10" text="Y" top="0" width="30"/>
						<Layout code="N" height="20" left="60" text="N" top="0" width="30"/>
					</Contents>
				</Radio>
			</Contents>
		</Div>
		<Div Border="Raised" Height="67" Id="Div14" Left="59" Style="sty_div_search" TabOrder="20" Text="질의내용" Top="252" Width="150">
			<Contents>
				<Static Align="Center" Height="40" Id="Static0" Left="7" TabOrder="1" Text="벨소리&#32;불량" Top="12" VAlign="Middle" Width="132" WordWrap="TRUE"></Static>
			</Contents>
		</Div>
		<Div Border="Raised" Height="67" Id="Div15" Left="536" Style="sty_div_search" TabOrder="21" Text="질의내용" Top="252" Width="150">
			<Contents>
				<Static Align="Center" Height="29" Id="Static0" Left="7" TabOrder="1" Text="진동&#32;불량" Top="17" VAlign="Middle" Width="127" WordWrap="TRUE"></Static>
			</Contents>
		</Div>
		<Div Border="Raised" Height="67" Id="div_choice5" Left="683" Style="sty_div_search" TabOrder="22" Text="질의내용" Top="252" Width="333">
			<Contents>
				<Radio BindDataset="ds_saleEqpSt" Border="None" CodeColumn="code" Column="VIBRATION_ST" ColumnCount="2" DataColumn="value" Height="50" Id="rdo_vibration" INDEX="-1" InnerDataset="ds_rdoVibration" Left="4" LeftMargin="5" OnChanged="f_st_set" RightMargin="50" Style="sty_opt_search" TabOrder="1" Top="6" Value="N" Width="320">
					<Contents>
						<Layout code="Y" height="20" left="10" text="Y" top="0" width="30"/>
						<Layout code="N" height="20" left="60" text="N" top="0" width="30"/>
					</Contents>
				</Radio>
			</Contents>
		</Div>
		<Div Border="Raised" Height="67" Id="div_choice8" Left="683" Style="sty_div_search" TabOrder="23" Text="질의내용" Top="316" Width="333">
			<Contents>
				<Radio BindDataset="ds_saleEqpSt" Border="None" CodeColumn="code" Column="GYRO_ST" ColumnCount="2" DataColumn="value" Height="50" Id="rdo_gyro" INDEX="-1" InnerDataset="ds_rdoGyro" Left="3" LeftMargin="5" OnChanged="f_st_set" RightMargin="115" Style="sty_opt_search" TabOrder="1" Top="6" Value="N" Width="320">
					<Contents>
						<Layout code="Y" height="20" left="10" text="Y" top="0" width="30"/>
						<Layout code="N" height="20" left="60" text="N" top="0" width="30"/>
					</Contents>
				</Radio>
			</Contents>
		</Div>
		<Div Border="Raised" Height="67" Id="Div21" Left="536" Style="sty_div_search" TabOrder="24" Text="질의내용" Top="316" Width="150">
			<Contents>
				<Static Align="Center" Height="29" Id="Static0" Left="7" TabOrder="1" Text="자이로센서&#32;불량" Top="16" VAlign="Middle" Width="132" WordWrap="TRUE"></Static>
			</Contents>
		</Div>
		<Div Border="Raised" Height="67" Id="div_choice10" Left="683" Style="sty_div_search" TabOrder="25" Text="질의내용" Top="380" Width="333">
			<Contents>
				<Radio BindDataset="ds_saleEqpSt" Border="None" CodeColumn="code" Column="CAMERA_ST" ColumnCount="2" DataColumn="value" Height="50" Id="rdo_camera" INDEX="-1" InnerDataset="ds_rdoCamera" Left="3" LeftMargin="5" OnChanged="f_st_set" RightMargin="5" Style="sty_opt_search" TabOrder="1" Top="6" Value="N" Width="320">
					<Contents>
						<Layout code="Y" height="20" left="10" text="Y" top="0" width="30"/>
						<Layout code="N" height="20" left="60" text="N" top="0" width="30"/>
					</Contents>
				</Radio>
			</Contents>
		</Div>
		<Div Border="Raised" Height="67" Id="Div24" Left="536" Style="sty_div_search" TabOrder="26" Text="질의내용" Top="380" Width="150">
			<Contents>
				<Static Align="Center" Height="40" Id="Static0" Left="7" TabOrder="1" Text="카메라&#32;불량&#13;&#10;(전면&#32;및&#32;후면)" Top="10" VAlign="Middle" Width="132" WordWrap="TRUE"></Static>
			</Contents>
		</Div>
		<Div Border="Raised" Height="67" Id="div_choice12" Left="683" Style="sty_div_search" TabOrder="27" Text="질의내용" Top="444" Width="333">
			<Contents>
				<Radio BindDataset="ds_saleEqpSt" Border="None" CodeColumn="code" Column="AFTERIMAGE_ST" ColumnCount="2" DataColumn="value" Height="50" Id="rdo_afterimage" INDEX="-1" InnerDataset="ds_rdoAfterimage" Left="3" LeftMargin="5" OnChanged="f_st_set" RightMargin="40" Style="sty_opt_search" TabOrder="1" Top="6" Value="N" Width="320">
					<Contents>
						<Layout code="Y" height="20" left="10" text="Y" top="0" width="30"/>
						<Layout code="N" height="20" left="60" text="N" top="0" width="30"/>
					</Contents>
				</Radio>
			</Contents>
		</Div>
		<Div Border="Raised" Height="67" Id="Div27" Left="536" Style="sty_div_search" TabOrder="28" Text="질의내용" Top="444" Width="150">
			<Contents>
				<Static Align="Center" Height="29" Id="Static0" Left="6" TabOrder="1" Text="잔상&#32;불량" Top="17" VAlign="Middle" Width="132" WordWrap="TRUE"></Static>
			</Contents>
		</Div>
		<Div Border="Raised" Height="67" Id="Div29" Left="682" Style="sty_div_search" TabOrder="29" Text="질의내용" Top="508" Width="334">
			<Contents>
				<Radio BindDataset="ds_saleEqpSt" Border="None" CodeColumn="code" Column="WIFI_ST" ColumnCount="2" DataColumn="value" Height="50" Id="rdo_wifi" INDEX="-1" InnerDataset="ds_rdoWifi" Left="3" LeftMargin="5" OnChanged="f_st_set" RightMargin="113" Style="sty_opt_search" TabOrder="1" Top="6" Value="N" Width="320">
					<Contents>
						<Layout code="Y" height="20" left="10" text="Y" top="0" width="30"/>
						<Layout code="N" height="20" left="60" text="N" top="0" width="30"/>
					</Contents>
				</Radio>
			</Contents>
		</Div>
		<Div Border="Raised" Height="67" Id="Div30" Left="535" Style="sty_div_search" TabOrder="30" Text="질의내용" Top="508" Width="150">
			<Contents>
				<Static Align="Center" Height="29" Id="Static0" Left="7" TabOrder="1" Text="WIFI&#32;불량" Top="16" VAlign="Middle" Width="132" WordWrap="TRUE"></Static>
			</Contents>
		</Div>
		<Div Border="Raised" Height="67" Id="Div32" Left="206" Style="sty_div_search" TabOrder="31" Text="질의내용" Top="572" Width="333">
			<Contents>
				<Radio BindDataset="ds_saleEqpSt" Border="None" CodeColumn="code" Column="STAIN_ST" ColumnCount="2" DataColumn="value" Height="50" Id="rdo_stain" INDEX="-1" InnerDataset="ds_rdoStain" Left="3" LeftMargin="5" OnChanged="f_st_set" RightMargin="50" Style="sty_opt_search" TabOrder="1" Top="6" Value="N" Width="320">
					<Contents>
						<Layout code="Y" height="20" left="10" text="Y" top="0" width="30"/>
						<Layout code="N" height="20" left="60" text="N" top="0" width="30"/>
					</Contents>
				</Radio>
			</Contents>
		</Div>
		<Div Border="Raised" Height="67" Id="Div33" Left="59" Style="sty_div_search" TabOrder="32" Text="질의내용" Top="572" Width="150">
			<Contents>
				<Static Align="Center" Height="40" Id="Static0" Left="6" TabOrder="1" Text="얼룩(흰색)" Top="11" VAlign="Middle" Width="132" WordWrap="TRUE"></Static>
			</Contents>
		</Div>
		<Div Border="Raised" Height="67" Id="Div34" Left="536" Style="sty_div_search" TabOrder="33" Text="질의내용" Top="572" Width="150">
			<Contents>
				<Static Align="Center" Height="40" Id="Static0" Left="6" TabOrder="1" Text="멍(자주색/오렌지색)" Top="13" VAlign="Middle" Width="135" WordWrap="TRUE"></Static>
			</Contents>
		</Div>
		<Div Border="Raised" Height="67" Id="Div35" Left="206" Style="sty_div_search" TabOrder="34" Text="질의내용" Top="636" Width="333">
			<Contents>
				<Radio BindDataset="ds_saleEqpSt" Border="None" CodeColumn="code" Column="SQUASH_ST" ColumnCount="2" DataColumn="value" Height="50" Id="rdo_squash" INDEX="-1" InnerDataset="ds_rdoSquash" Left="3" LeftMargin="5" OnChanged="f_st_set" RightMargin="115" Style="sty_opt_search" TabOrder="1" Top="6" Value="N" Width="320">
					<Contents>
						<Layout code="Y" height="20" left="10" text="Y" top="0" width="30"/>
						<Layout code="N" height="20" left="60" text="N" top="0" width="30"/>
					</Contents>
				</Radio>
			</Contents>
		</Div>
		<Div Border="Raised" Height="67" Id="Div36" Left="59" Style="sty_div_search" TabOrder="35" Text="질의내용" Top="636" Width="150">
			<Contents>
				<Static Align="Center" Height="27" Id="Static0" Left="7" TabOrder="1" Text="눌림" Top="18" VAlign="Middle" Width="132" WordWrap="TRUE"></Static>
			</Contents>
		</Div>
		<Div Border="Raised" Height="67" Id="Div38" Left="683" Style="sty_div_search" TabOrder="36" Text="질의내용" Top="572" Width="333">
			<Contents>
				<Radio BindDataset="ds_saleEqpSt" Border="None" CodeColumn="code" Column="BRUISE_ST" ColumnCount="2" DataColumn="value" Height="50" Id="rdo_bruise" INDEX="-1" InnerDataset="ds_rdoBruise" Left="3" LeftMargin="5" OnChanged="f_st_set" RightMargin="60" Style="sty_opt_search" TabOrder="1" Top="6" Value="N" Width="320">
					<Contents>
						<Layout code="Y" height="20" left="10" text="Y" top="0" width="30"/>
						<Layout code="N" height="20" left="60" text="N" top="0" width="30"/>
					</Contents>
				</Radio>
			</Contents>
		</Div>
		<Div Border="Raised" Height="67" Id="Div40" Left="206" Style="sty_div_search" TabOrder="37" Text="질의내용" Top="700" Width="810">
			<Contents>
				<Radio BindDataset="ds_saleEqpSt" Border="None" CodeColumn="code" Column="LED_ST" ColumnCount="2" DataColumn="value" Height="50" Id="rdo_led" INDEX="-1" InnerDataset="ds_rdoLed" Left="3" LeftMargin="5" OnChanged="f_st_set" RightMargin="70" Style="sty_opt_search" TabOrder="1" Top="6" Value="N" Width="320">
					<Contents>
						<Layout code="Y" height="20" left="10" text="Y" top="0" width="30"/>
						<Layout code="N" height="20" left="60" text="N" top="0" width="30"/>
					</Contents>
				</Radio>
			</Contents>
		</Div>
		<Div Border="Raised" Height="67" Id="Div41" Left="59" Style="sty_div_search" TabOrder="38" Text="질의내용" Top="700" Width="150">
			<Contents>
				<Static Align="Center" Height="29" Id="Static0" Left="7" TabOrder="1" Text="LCD파손" Top="16" VAlign="Middle" Width="132" WordWrap="TRUE"></Static>
			</Contents>
		</Div>
		<Div Border="Raised" Height="92" Id="Div11" Left="206" Style="sty_div_search" TabOrder="39" Text="질의내용" Top="764" Width="333">
			<Contents>
				<Radio BindDataset="ds_saleEqpSt" Border="None" CodeColumn="code" Column="BUTTON_ST" DataColumn="value" Height="78" Id="rdo_button" INDEX="-1" InnerDataset="ds_rdoButton" Left="3" LeftMargin="5" OnChanged="f_st_set" RightMargin="40" Style="sty_opt_search" TabOrder="1" Top="4" Value="N" Width="320">
					<Contents>
						<Layout code="Y" height="20" left="10" text="Y" top="0" width="30"/>
						<Layout code="N" height="20" left="60" text="N" top="0" width="30"/>
					</Contents>
				</Radio>
			</Contents>
		</Div>
		<Div Border="Raised" Height="92" Id="Div31" Left="59" Style="sty_div_search" TabOrder="40" Text="질의내용" Top="764" Width="150">
			<Contents>
				<Static Align="Center" Height="40" Id="Static0" Left="7" TabOrder="1" Text="버튼&#32;불량" Top="28" VAlign="Middle" Width="132" WordWrap="TRUE"></Static>
			</Contents>
		</Div>
		<Div Border="Raised" Height="92" Id="Div42" Left="536" Style="sty_div_search" TabOrder="41" Text="질의내용" Top="764" Width="150">
			<Contents>
				<Static Align="Center" Height="29" Id="Static0" Left="7" TabOrder="1" Text="하단터치메뉴" Top="17" VAlign="Middle" Width="127" WordWrap="TRUE"></Static>
			</Contents>
		</Div>
		<Div Border="Raised" Height="67" Id="Div43" Left="206" Style="sty_div_search" TabOrder="42" Text="질의내용" Top="852" Width="333">
			<Contents>
				<Radio BindDataset="ds_saleEqpSt" Border="None" CodeColumn="code" Column="BODY_ST" ColumnCount="2" DataColumn="value" Height="50" Id="rdo_body" INDEX="-1" InnerDataset="ds_rdoBody" Left="3" LeftMargin="5" OnChanged="f_st_set" RightMargin="125" Style="sty_opt_search" TabOrder="1" Top="6" Value="N" Width="320">
					<Contents>
						<Layout code="Y" height="20" left="10" text="Y" top="0" width="30"/>
						<Layout code="N" height="20" left="60" text="N" top="0" width="30"/>
					</Contents>
				</Radio>
			</Contents>
		</Div>
		<Div Border="Raised" Height="67" Id="Div44" Left="59" Style="sty_div_search" TabOrder="43" Text="질의내용" Top="852" Width="150">
			<Contents>
				<Static Align="Center" Height="27" Id="Static0" Left="7" TabOrder="1" Text="몸체&#32;미세&#32;휨" Top="18" VAlign="Middle" Width="132" WordWrap="TRUE"></Static>
			</Contents>
		</Div>
		<Div Border="Raised" Height="92" Id="Div46" Left="683" Style="sty_div_search" TabOrder="44" Text="질의내용" Top="764" Width="333">
			<Contents>
				<Radio BindDataset="ds_saleEqpSt" Border="None" CodeColumn="code" Column="BOTTOM_ST" ColumnCount="2" DataColumn="value" Height="76" Id="rdo_bottom" INDEX="-1" InnerDataset="ds_rdoBottom" Left="3" LeftMargin="5" OnChanged="f_st_set" RightMargin="50" Style="sty_opt_search" TabOrder="1" Top="4" Value="N" Width="320">
					<Contents>
						<Layout code="Y" height="20" left="10" text="Y" top="0" width="30"/>
						<Layout code="N" height="20" left="60" text="N" top="0" width="30"/>
					</Contents>
				</Radio>
			</Contents>
		</Div>
		<Div Border="Raised" Height="67" Id="Div47" Left="206" Style="sty_div_search" TabOrder="45" Text="질의내용" Top="916" Width="333">
			<Contents>
				<Radio BindDataset="ds_saleEqpSt" Border="None" CodeColumn="code" Column="GLASS_ST" ColumnCount="2" DataColumn="value" Height="50" Id="rdo_glass" INDEX="-1" InnerDataset="ds_rdoGlass" Left="3" LeftMargin="5" OnChanged="f_st_set" RightMargin="71" Style="sty_opt_search" TabOrder="1" Top="6" Value="N" Width="320">
					<Contents>
						<Layout code="Y" height="20" left="10" text="Y" top="0" width="30"/>
						<Layout code="N" height="20" left="60" text="N" top="0" width="30"/>
					</Contents>
				</Radio>
			</Contents>
		</Div>
		<Div Border="Raised" Height="67" Id="Div48" Left="59" Style="sty_div_search" TabOrder="46" Text="질의내용" Top="916" Width="150">
			<Contents>
				<Static Align="Center" Height="29" Id="Static0" Left="7" TabOrder="1" Text="액정유리(터치판넬)" Top="16" VAlign="Middle" Width="132" WordWrap="TRUE"></Static>
			</Contents>
		</Div>
		<Div Border="Raised" Height="67" Id="Div51" Left="59" Style="sty_div_search" TabOrder="47" Text="질의내용" Top="980" Width="150">
			<Contents>
				<Static Align="Center" Height="41" Id="Static0" Left="7" TabOrder="1" Text="카메라&#32;윈도우&#32;손상&#13;&#10;(좁쌀이나감/바늘구멍)" Top="11" VAlign="Middle" Width="132" WordWrap="TRUE"></Static>
			</Contents>
		</Div>
		<Div Border="Raised" Height="284" Id="Div53" Left="6" Style="sty_div_search" TabOrder="48" Text="질의내용" Top="764" Width="56">
			<Contents>
				<Static Align="Right" Height="82" Id="Static4" Left="6" Style="sty_lb_Search" TabOrder="1" Text="외관&#10;점검" Top="108" VAlign="Middle" Width="32" WordWrap="TRUE"></Static>
			</Contents>
		</Div>
		<Div Border="Raised" Height="62" Id="Div39" Left="6" Style="sty_div_search" TabOrder="49" Text="질의내용" Top="1044" Width="56">
			<Contents>
				<Static Align="Right" Height="32" Id="Static4" Left="6" Style="sty_lb_Search" TabOrder="1" Text="반송" Top="14" VAlign="Middle" Width="32" WordWrap="TRUE"></Static>
			</Contents>
		</Div>
		<Div Border="Raised" Height="62" Id="Div54" Left="206" Style="sty_div_search" TabOrder="50" Text="질의내용" Top="1044" Width="810">
			<Contents>
				<Radio BindDataset="ds_saleEqpSt" Border="None" CodeColumn="code" Column="RETURN_ST" ColumnCount="2" DataColumn="value" Height="50" Id="rdo_return" INDEX="-1" InnerDataset="ds_rdoReturn" Left="3" LeftMargin="5" RightMargin="100" Style="sty_opt_search" TabOrder="1" Top="3" Value="N" Width="320">
					<Contents>
						<Layout code="Y" height="20" left="10" text="Y" top="0" width="30"/>
						<Layout code="N" height="20" left="60" text="N" top="0" width="30"/>
					</Contents>
				</Radio>
			</Contents>
		</Div>
		<Div Border="Raised" Height="62" Id="Div55" Left="59" Style="sty_div_search" TabOrder="51" Text="질의내용" Top="1044" Width="150">
			<Contents>
				<Checkbox BindDataset="ds_saleEqpSt" Column="RETURN_CL" Height="34" Id="chk_returnYn" Left="18" LeftMargin="5" OnClick="Div55_chk_returnYn_OnClick" Style="sty_opt_search" TabOrder="1" Text="매입불가" Top="10" Width="96"></Checkbox>
			</Contents>
		</Div>
		<Div Border="Raised" Height="67" Id="Div4" Left="59" Style="sty_div_search" TabOrder="52" Text="질의내용" Top="316" Width="150">
			<Contents>
				<Static Align="Center" Height="29" Id="Static0" Left="7" TabOrder="1" Text="조도센서&#32;불량" Top="16" VAlign="Middle" Width="128" WordWrap="TRUE"></Static>
			</Contents>
		</Div>
		<Div Border="Raised" Height="67" Id="div_choice7" Left="206" Style="sty_div_search" TabOrder="53" Text="질의내용" Top="316" Width="333">
			<Contents>
				<Radio BindDataset="ds_saleEqpSt" Border="None" CodeColumn="code" Column="JODO_ST" ColumnCount="2" DataColumn="value" Height="50" Id="rdo_jodo" INDEX="-1" InnerDataset="ds_rdoJodo" Left="4" LeftMargin="5" OnChanged="f_st_set" RightMargin="115" Style="sty_opt_search" TabOrder="1" Top="6" Value="N" Width="320">
					<Contents>
						<Layout code="Y" height="20" left="10" text="Y" top="0" width="30"/>
						<Layout code="N" height="20" left="60" text="N" top="0" width="30"/>
					</Contents>
				</Radio>
			</Contents>
		</Div>
		<Div Border="Raised" Height="67" Id="Div9" Left="59" Style="sty_div_search" TabOrder="54" Text="질의내용" Top="380" Width="150">
			<Contents>
				<Static Align="Center" Height="28" Id="Static0" Left="8" TabOrder="1" Text="근접센서&#32;불량" Top="18" VAlign="Middle" Width="128" WordWrap="TRUE"></Static>
			</Contents>
		</Div>
		<Div Border="Raised" Height="67" Id="div_choice9" Left="206" Style="sty_div_search" TabOrder="55" Text="질의내용" Top="380" Width="333">
			<Contents>
				<Radio BindDataset="ds_saleEqpSt" Border="None" CodeColumn="code" Column="PROXIMITY_ST" ColumnCount="2" DataColumn="value" Height="50" Id="rdo_proximity" INDEX="-1" InnerDataset="ds_rdoProximity" Left="3" LeftMargin="5" OnChanged="f_st_set" RightMargin="115" Style="sty_opt_search" TabOrder="1" Top="5" Value="N" Width="320">
					<Contents>
						<Layout code="Y" height="20" left="10" text="Y" top="0" width="30"/>
						<Layout code="N" height="20" left="60" text="N" top="0" width="30"/>
					</Contents>
				</Radio>
			</Contents>
		</Div>
		<Div Border="Raised" Height="67" Id="Div13" Left="59" Style="sty_div_search" TabOrder="56" Text="질의내용" Top="444" Width="150">
			<Contents>
				<Static Align="Center" Height="24" Id="Static0" Left="8" TabOrder="1" Text="B/T&#32;불량" Top="19" VAlign="Middle" Width="128" WordWrap="TRUE"></Static>
			</Contents>
		</Div>
		<Div Border="Raised" Height="67" Id="div_choice11" Left="206" Style="sty_div_search" TabOrder="57" Text="질의내용" Top="444" Width="333">
			<Contents>
				<Radio BindDataset="ds_saleEqpSt" Border="None" CodeColumn="code" Column="BATTERY_ST" ColumnCount="2" DataColumn="value" Height="50" Id="rdo_battery" INDEX="-1" InnerDataset="ds_rdoBattery" Left="4" LeftMargin="5" OnChanged="f_st_set" RightMargin="117" Style="sty_opt_search" TabOrder="1" Top="5" Value="N" Width="320">
					<Contents>
						<Layout code="Y" height="20" left="10" text="Y" top="0" width="30"/>
						<Layout code="N" height="20" left="60" text="N" top="0" width="30"/>
					</Contents>
				</Radio>
			</Contents>
		</Div>
		<Div Border="Raised" Height="67" Id="Div16" Left="59" Style="sty_div_search" TabOrder="58" Text="질의내용" Top="508" Width="150">
			<Contents>
				<Static Align="Center" Height="27" Id="Static0" Left="7" TabOrder="1" Text="터치불량&#13;&#10;(세부)" Top="19" VAlign="Middle" Width="132" WordWrap="TRUE"></Static>
			</Contents>
		</Div>
		<Div Border="Raised" Height="67" Id="Div19" Left="206" Style="sty_div_search" TabOrder="59" Text="질의내용" Top="508" Width="333">
			<Contents>
				<Radio BindDataset="ds_saleEqpSt" Border="None" CodeColumn="code" Column="TOUCH_ST" ColumnCount="2" DataColumn="value" Height="50" Id="rdo_touch" INDEX="-1" InnerDataset="ds_rdoTouch" Left="4" LeftMargin="5" OnChanged="f_st_set" RightMargin="57" Style="sty_opt_search" TabOrder="1" Top="5" Value="N" Width="320">
					<Contents>
						<Layout code="Y" height="20" left="10" text="Y" top="0" width="30"/>
						<Layout code="N" height="20" left="60" text="N" top="0" width="30"/>
					</Contents>
				</Radio>
			</Contents>
		</Div>
		<Div Border="Raised" Height="67" Id="Div18" Left="536" Style="sty_div_search" TabOrder="61" Text="질의내용" Top="636" Width="150">
			<Contents>
				<Static Align="Center" Height="29" Id="Static0" Left="7" TabOrder="1" Text="액상유입" Top="13" VAlign="Middle" Width="128" WordWrap="TRUE"></Static>
			</Contents>
		</Div>
		<Div Border="Raised" Height="67" Id="Div20" Left="683" Style="sty_div_search" TabOrder="60" Text="질의내용" Top="636" Width="333">
			<Contents>
				<Radio BindDataset="ds_saleEqpSt" Border="None" CodeColumn="code" Column="LIQUEFIED_ST" ColumnCount="2" DataColumn="value" Height="50" Id="rdo_liquefied" INDEX="-1" InnerDataset="ds_rdoLiquefied" Left="3" LeftMargin="5" OnChanged="f_st_set" RightMargin="25" Style="sty_opt_search" TabOrder="1" Top="5" Value="N" Width="320">
					<Contents>
						<Layout code="Y" height="20" left="10" text="Y" top="0" width="30"/>
						<Layout code="N" height="20" left="60" text="N" top="0" width="30"/>
					</Contents>
				</Radio>
			</Contents>
		</Div>
		<Div Border="Raised" Height="67" Id="Div22" Left="536" Style="sty_div_search" TabOrder="62" Text="질의내용" Top="852" Width="150">
			<Contents>
				<Static Align="Center" Height="45" Id="Static0" Left="9" TabOrder="1" Text="DMB안테나&#32;손상" Top="8" VAlign="Middle" Width="132" WordWrap="TRUE"></Static>
			</Contents>
		</Div>
		<Div Border="Raised" Height="67" Id="Div23" Left="683" Style="sty_div_search" TabOrder="63" Text="질의내용" Top="852" Width="333">
			<Contents>
				<Radio BindDataset="ds_saleEqpSt" Border="None" CodeColumn="code" Column="DMB_ST" ColumnCount="2" DataColumn="value" Height="50" Id="rdo_dmb" INDEX="-1" InnerDataset="ds_rdoDmb" Left="3" LeftMargin="5" OnChanged="f_st_set" RightMargin="35" Style="sty_opt_search" TabOrder="1" Top="5" Value="N" Width="320">
					<Contents>
						<Layout code="Y" height="20" left="10" text="Y" top="0" width="30"/>
						<Layout code="N" height="20" left="60" text="N" top="0" width="30"/>
					</Contents>
				</Radio>
			</Contents>
		</Div>
		<Div Border="Raised" Height="67" Id="Div25" Left="536" Style="sty_div_search" TabOrder="64" Text="질의내용" Top="916" Width="150">
			<Contents>
				<Static Align="Center" Height="28" Id="Static0" Left="8" TabOrder="1" Text="이나감" Top="18" VAlign="Middle" Width="128" WordWrap="TRUE"></Static>
			</Contents>
		</Div>
		<Div Border="Raised" Height="67" Id="Div26" Left="683" Style="sty_div_search" TabOrder="65" Text="질의내용" Top="916" Width="333">
			<Contents>
				<Radio BindDataset="ds_saleEqpSt" Border="None" CodeColumn="code" Column="TEETH_ST" ColumnCount="2" DataColumn="value" Height="50" Id="rdo_teeth" INDEX="-1" InnerDataset="ds_rdoTeeth" Left="3" LeftMargin="5" OnChanged="f_st_set" RightMargin="95" Style="sty_opt_search" TabOrder="1" Top="6" Value="N" Width="320">
					<Contents>
						<Layout code="Y" height="20" left="10" text="Y" top="0" width="30"/>
						<Layout code="N" height="20" left="60" text="N" top="0" width="30"/>
					</Contents>
				</Radio>
			</Contents>
		</Div>
		<Div Border="Raised" Height="67" Id="Div28" Left="536" Style="sty_div_search" TabOrder="67" Text="질의내용" Top="980" Width="150">
			<Contents>
				<Static Align="Center" Height="40" Id="Static0" Left="9" TabOrder="1" Text="테두리&#32;및&#32;몸체&#13;&#10;(벗겨짐/찍힘)" Top="11" VAlign="Middle" Width="128" WordWrap="TRUE"></Static>
			</Contents>
		</Div>
		<Div Border="Raised" Height="67" Id="Div37" Left="683" Style="sty_div_search" TabOrder="66" Text="질의내용" Top="980" Width="333">
			<Contents>
				<Radio BindDataset="ds_saleEqpSt" Border="None" CodeColumn="code" Column="EDGE_ST" ColumnCount="2" DataColumn="value" Height="50" Id="rdo_edge" INDEX="-1" InnerDataset="ds_rdoEdge" Left="4" LeftMargin="5" OnChanged="f_st_set" RightMargin="1" Style="sty_opt_search" TabOrder="1" Top="5" Value="N" Width="320">
					<Contents>
						<Layout code="Y" height="20" left="10" text="Y" top="0" width="30"/>
						<Layout code="N" height="20" left="60" text="N" top="0" width="30"/>
					</Contents>
				</Radio>
			</Contents>
		</Div>
		<Div Border="Raised" Height="67" Id="Div50" Left="206" Style="sty_div_search" TabOrder="68" Text="질의내용" Top="980" Width="333">
			<Contents>
				<Radio BindDataset="ds_saleEqpSt" Border="None" CodeColumn="code" Column="WINDOW_ST" ColumnCount="2" DataColumn="value" Height="50" Id="rdo_window" INDEX="-1" InnerDataset="ds_rdoWindow" Left="3" LeftMargin="5" OnChanged="f_st_set" RightMargin="109" Style="sty_opt_search" TabOrder="1" Top="6" Value="N" Width="320">
					<Contents>
						<Layout code="Y" height="20" left="10" text="Y" top="0" width="30"/>
						<Layout code="N" height="20" left="60" text="N" top="0" width="30"/>
					</Contents>
				</Radio>
			</Contents>
		</Div>
		<Div Border="Raised" Height="86" Id="Div17" Left="536" Style="sty_div_search" TabOrder="69" Text="질의내용" Top="172" Width="150">
			<Contents>
				<Static Align="Center" Height="40" Id="Static0" Left="12" TabOrder="1" Text="구성품&#32;없음" Top="20" VAlign="Middle" Width="121" WordWrap="TRUE"></Static>
			</Contents>
		</Div>
		<Div Border="Raised" Height="86" Id="div_choice6" Left="683" Style="sty_div_search" TabOrder="70" Text="질의내용" Top="172" Width="333">
			<Contents>
				<Radio BindDataset="ds_saleEqpSt" Border="None" CodeColumn="code" Column="CPNT_ST" ColumnCount="2" DataColumn="value" Height="68" Id="rdo_cpnt" INDEX="-1" InnerDataset="ds_rdoCpnt" Left="3" LeftMargin="5" OnChanged="f_st_set" RightMargin="100" Style="sty_opt_search" TabOrder="1" Top="6" Value="N" Width="320">
					<Contents>
						<Layout code="Y" height="20" left="10" text="Y" top="0" width="30"/>
						<Layout code="N" height="20" left="60" text="N" top="0" width="30"/>
					</Contents>
				</Radio>
			</Contents>
		</Div>
	</Form>
	<Script><![CDATA[/*******************************************************************************
* 프로그램ID 	: 
* 업무명      	: 중고단말기영업 - 상담등록
* 프로그램명  	: 상담목록조회
--------------------------------------------------------------------------------
* 작성자      	: 민동운
* 작성일      	: 2011.07.11
--------------------------------------------------------------------------------
* 1. 변경이력
*******************************************************************************/

/*******************************************************************************
//  감가상각금액  =  출고가 * (사용일수 * 0.000913)
//  상계계수금액  =  출고가 / 상계계수(%)
//  기준금액      =  감가상각금액 와 상계계수금액 중 작은 금액
//  선호도금액    =  기준금액 / 선호도(%)
//  등급급액 계산 =  선호도금액 / 등급(%)
*******************************************************************************/
/*******************************************************************************
//   FV_PRC_GB
//   'N' 검수대상목록
//   'P' 매입제외목록
*******************************************************************************/
//==============================================================================
// 공통 스크립트 로딩
//==============================================================================
#include "lib::lib_commF.js"
#include "lib::lib_commMsg.js"
#include "lib::lib_commPopup.js"
#include "lib::lib_SAL.js"
#include "lib::lib_util.js"
//==============================================================================
// 폼 변수 정의 
//==============================================================================
// 글로벌 세션정보
var FV_USER_ID;					// 사용자ID
var FV_USER_NM;					// 사용자명

var	FV_ORG_ID;					// 소속 
var	FV_ORG_NM;					// 소속명
var	FV_ORG_CL;					// 소속구분
var	FV_AGENCY_ID;           	// 소속 팀ID
var	FV_AGENCY_NM;           	// 소속 팀명
var	FV_AGENCY_UKEY_ID;      	// 소속 팀UKEY ID	
	
var	FV_ORG_AREA_ID;				// 근무지 ID
var	FV_ORG_AREA_NM;				// 근무지명
var	FV_ORG_AREA_POS_AGENCY_CD;	// 근무지 
var	FV_ORG_AREA_UKEY_ID;     	// 근무지ukeyid
var	FV_ORG_AREA_SUB_CD;      	// 근무지subcd
var	FV_ORG_AREA_CHANNEL_CD;  	// 근무지 channelcd	
var	FV_USER_GRP;			 	// 유저그룹

var	FV_DUTY;					// 사용자 직책
var	FV_ORG_AREA_CL1;			// 근무지 구분

var	FV_CON_MGMT_NO = "";
var	FV_SALE_EQP_ST = "";
var	FV_EQP_ST = "";
var FV_JOIN_WAY = "";
var FV_EQP_E = "";
var FV_USIM_EQP_E = "";


/*******************************************************************************
 * @description    : 최초 폼 로드시 발생 - 이벤트
*******************************************************************************/
function CSTSKN01500_OnLoadCompleted(obj)
{

	f_getSession();

	//f_rdo_setting();
	//div_conInfo8.edt_saleEqpSt.Text = 'A+';

	lf_formVarInit();

	div_conInfo8.edt_conMgmtNo = FV_CON_MGMT_NO;

	if(FV_JOIN_WAY == "C"){
		div_conInfo8.sta_joinWay.Value = "기변";			
	}

	f_getSale_eqp();

}

/*******************************************************************************
 * @description    : 글로벌 섹션 정보
*******************************************************************************/
function f_getSession()
{
	FV_USER_ID        = gds_session.GetColumn(0, "loginid");						// 사용자ID
	FV_USER_NM        = gds_session.GetColumn(0, "usernm");							// 사용자명

	FV_ORG_ID         = gds_session.GetColumn(0, "orgid");							// 소속 
	FV_ORG_NM         = gds_session.GetColumn(0, "orgnm");							// 소속명
	FV_ORG_CL         = gds_session.GetColumn(0, "orgcl");							// 소속구분
	FV_AGENCY_ID      = gds_session.GetColumn(0, "posAgencyId");        			// 소속 팀ID
	FV_AGENCY_NM      = gds_session.GetColumn(0, "posAgencyNm");        			// 소속 팀명
	FV_AGENCY_UKEY_ID = gds_session.GetColumn(0, "posAgencyUkeyId");    			// 소속 팀UKEY ID	
	
	FV_ORG_AREA_ID            = gds_session.GetColumn(0, "orgareaid");				// 근무지 ID
	FV_ORG_AREA_NM            = gds_session.GetColumn(0, "orgareanm");				// 근무지명
	FV_ORG_AREA_POS_AGENCY_CD = gds_session.GetColumn(0, "orgareaposagencycd");		// 근무지 
	FV_ORG_AREA_UKEY_ID       = gds_session.GetColumn(0, "orgareaukeyid");      	// 근무지ukeyid
	FV_ORG_AREA_SUB_CD        = gds_session.GetColumn(0, "orgareaukeysubcd");   	// 근무지subcd
	FV_ORG_AREA_CHANNEL_CD    = gds_session.GetColumn(0, "orgareaukeychannelcd"); 	// 근무지 channelcd	
	FV_USER_GRP               = gds_session.GetColumn(0, "usergrp");				// 유저그룹
	
	FV_ORG_AREA_CL1           = gds_session.GetColumn(0, "orgareacl1");				// 근무지 구분
	FV_DUTY                   = gds_session.GetColumn(0, "duty");	   		    	// 직책		
}


/*******************************************************************************
 * @description         : 로컬 변수 초기화 초기화
*******************************************************************************/
function lf_formVarInit()
{    
    if(IsExistVar("p_con_mgmt_no",true)){ FV_CON_MGMT_NO = p_con_mgmt_no; } 
    if(IsExistVar("p_join_way",true)){ FV_JOIN_WAY = p_join_way; } 
}


/*******************************************************************************
 * @description         : radio Button 초기화
*******************************************************************************/
function f_rdo_setting()
{
	div_choice1.rdo_power.value = '11';
	div_choice2.rdo_charge.value = '11';
	div_choice3.rdo_usim.value = '11';
	div_choice4.rdo_bell.value = '11';
	div_choice5.rdo_vibration.value = '11';
	div_choice6.rdo_cpnt.value = '11';
	div_choice7.rdo_jodo.value = '11';
	div_choice8.rdo_gyro.value = '11';
	div_choice9.rdo_proximity.value = '11';
	div_choice10.rdo_camera.value = '11';
	div_choice11.rdo_battery.value = '11';
	div_choice12.rdo_afterimage.value = '11';
	Div19.rdo_touch.value = '11';
	Div29.rdo_wifi.value = '11';
	Div32.rdo_stain.value = '11';
	Div38.rdo_bruise.value = '11';
	Div35.rdo_squash.value = '11';
	Div20.rdo_liquefied.value = '11';
	Div40.rdo_led.value = '11';
	Div11.rdo_button.value = '11';
	Div46.rdo_bottom.value = '11';
	Div43.rdo_body.value = '11';
	Div23.rdo_dmb.value = '11';
	Div47.rdo_glass.value = '11';
	Div26.rdo_proximity.value = '11';
	Div37.rdo_edge.value = '11';
}

/*******************************************************************************
 * @description         : 판매등급결정
*******************************************************************************/
function f_st_set()
{

	if(Div55.chk_returnYn.Value == "1") {
	}else{
	
		FV_SALE_EQP_ST = Left(div_choice1.rdo_power.value, 1);
		FV_EQP_ST = Right(div_choice1.rdo_power.value, 1);
		if ( Right(div_choice1.rdo_power.value, 1) == '3') {
			FV_EQP_E = 'Y';
		}
		
		if ( FV_SALE_EQP_ST < Left(div_choice2.rdo_charge.value, 1) ) {
			FV_SALE_EQP_ST = Left(div_choice2.rdo_charge.value, 1);
		}
		if ( Right(div_choice2.rdo_charge.value, 1) == '3') {
			FV_EQP_E = 'Y';
		}
		if ( FV_EQP_ST < Right(div_choice2.rdo_charge.value, 1) ) {
			FV_EQP_ST = Right(div_choice2.rdo_charge.value, 1);
		}
		
		
		if ( FV_SALE_EQP_ST < Left(div_choice3.rdo_usim.value, 1) ) {
			FV_SALE_EQP_ST = Left(div_choice3.rdo_usim.value, 1);
		}
		if ( Right(div_choice3.rdo_usim.value, 1) == '3') {
			FV_USIM_EQP_E = 'Y';
		}
		if ( FV_EQP_ST < Right(div_choice3.rdo_usim.value, 1) ) {
			FV_EQP_ST = Right(div_choice3.rdo_usim.value, 1);
		}
		
		
		if ( FV_SALE_EQP_ST < Left(div_choice4.rdo_bell.value, 1) ) {
			FV_SALE_EQP_ST = Left(div_choice4.rdo_bell.value, 1);
		}
		if ( Right(div_choice4.rdo_bell.value, 1) == '3') {
			FV_EQP_E = 'Y';
		}		
		if ( FV_EQP_ST < Right(div_choice4.rdo_bell.value, 1) ) {
			FV_EQP_ST = Right(div_choice4.rdo_bell.value, 1);
		}
		
		
		if ( FV_SALE_EQP_ST < Left(div_choice5.rdo_vibration.value, 1) ) {
			FV_SALE_EQP_ST = Left(div_choice5.rdo_vibration.value, 1);
		}
		if ( Right(div_choice5.rdo_vibration.value, 1) == '3') {
			FV_EQP_E = 'Y';
		}		
		if ( FV_EQP_ST < Right(div_choice5.rdo_vibration.value, 1) ) {
			FV_EQP_ST = Right(div_choice5.rdo_vibration.value, 1);
		}
		
		
		if ( FV_SALE_EQP_ST < Left(div_choice6.rdo_cpnt.value, 1) ) {
			FV_SALE_EQP_ST = Left(div_choice6.rdo_cpnt.value, 1);
		}
		if ( Right(div_choice6.rdo_cpnt.value, 1) == '3') {
			FV_EQP_E = 'Y';
		}
		if ( FV_EQP_ST < Right(div_choice6.rdo_cpnt.value, 1) ) {
			FV_EQP_ST = Right(div_choice6.rdo_cpnt.value, 1);
		}
		
		
		if ( FV_SALE_EQP_ST < Left(div_choice7.rdo_jodo.value, 1) ) {
			FV_SALE_EQP_ST = Left(div_choice7.rdo_jodo.value, 1);
		}
		if ( Right(div_choice7.rdo_jodo.value, 1) == '3') {
			FV_EQP_E = 'Y';
		}
		if ( FV_EQP_ST < Right(div_choice7.rdo_jodo.value, 1) ) {
			FV_EQP_ST = Right(div_choice7.rdo_jodo.value, 1);
		}
		
		
		if ( FV_SALE_EQP_ST < Left(div_choice8.rdo_gyro.value, 1) ) {
			FV_SALE_EQP_ST = Left(div_choice8.rdo_gyro.value, 1);
		}
		if ( Right(div_choice8.rdo_gyro.value, 1) == '3') {
			FV_EQP_E = 'Y';
		}
		if ( FV_EQP_ST < Right(div_choice8.rdo_gyro.value, 1) ) {
			FV_EQP_ST = Right(div_choice8.rdo_gyro.value, 1);
		}
		
		
		if ( FV_SALE_EQP_ST < Left(div_choice9.rdo_proximity.value, 1) ) {
			FV_SALE_EQP_ST = Left(div_choice9.rdo_proximity.value, 1);
		}
		if ( Right(div_choice9.rdo_proximity.value, 1) == '3') {
			FV_EQP_E = 'Y';
		}
		if ( FV_EQP_ST < Right(div_choice9.rdo_proximity.value, 1) ) {
			FV_EQP_ST = Right(div_choice9.rdo_proximity.value, 1);
		}
		
			
		if ( FV_SALE_EQP_ST < Left(div_choice10.rdo_camera.value, 1) ) {
			FV_SALE_EQP_ST = Left(div_choice10.rdo_camera.value, 1);
		}
		if ( Left(div_choice10.rdo_camera.value, 1) == '5') {
			FV_EQP_E = 'Y';
		}
		if ( FV_EQP_ST < Right(div_choice10.rdo_camera.value, 1) ) {
			FV_EQP_ST = Right(div_choice10.rdo_camera.value, 1);
		}
		
		
		if ( FV_SALE_EQP_ST < Left(div_choice11.rdo_battery.value, 1) ) {
			FV_SALE_EQP_ST = Left(div_choice11.rdo_battery.value, 1);
		}
		if ( Right(div_choice11.rdo_battery.value, 1) == '3') {
			FV_EQP_E = 'Y';
		}
		if ( FV_EQP_ST < Right(div_choice11.rdo_battery.value, 1) ) {
			FV_EQP_ST = Right(div_choice11.rdo_battery.value, 1);
		}
		
		
		if ( FV_SALE_EQP_ST < Left(div_choice12.rdo_afterimage.value, 1) ) {
			FV_SALE_EQP_ST = Left(div_choice12.rdo_afterimage.value, 1);
		}
		if ( Right(div_choice12.rdo_afterimage.value, 1) == '3') {
			FV_EQP_E = 'Y';
		}
		if ( FV_EQP_ST < Right(div_choice12.rdo_afterimage.value, 1) ) {
			FV_EQP_ST = Right(div_choice12.rdo_afterimage.value, 1);
		}
		
		
		if ( FV_SALE_EQP_ST < Left(Div19.rdo_touch.value, 1) ) {
			FV_SALE_EQP_ST = Left(Div19.rdo_touch.value, 1);
		}
		if ( Right(Div19.rdo_touch.value, 1) == '3') {
			FV_EQP_E = 'Y';
		}
		if ( FV_EQP_ST < Right(Div19.rdo_touch.value, 1) ) {
			FV_EQP_ST = Right(Div19.rdo_touch.value, 1);
		}
		
		
		if ( FV_SALE_EQP_ST < Left(Div29.rdo_wifi.value, 1) ) {
			FV_SALE_EQP_ST = Left(Div29.rdo_wifi.value, 1);
		}
		if ( Right(Div29.rdo_wifi.value, 1) == '3') {
			FV_EQP_E = 'Y';
		}
		if ( FV_EQP_ST < Right(Div29.rdo_wifi.value, 1) ) {
			FV_EQP_ST = Right(Div29.rdo_wifi.value, 1);
		}
		
		
		if ( FV_SALE_EQP_ST < Left(Div32.rdo_stain.value, 1) ) {
			FV_SALE_EQP_ST = Left(Div32.rdo_stain.value, 1);
		}
		if ( Right(Div32.rdo_stain.value, 1) == '3') {
			FV_EQP_E = 'Y';
		}
		if ( FV_EQP_ST < Right(Div32.rdo_stain.value, 1) ) {
			FV_EQP_ST = Right(Div32.rdo_stain.value, 1);
		}
		
		
		if ( FV_SALE_EQP_ST < Left(Div38.rdo_bruise.value, 1) ) {
			FV_SALE_EQP_ST = Left(Div38.rdo_bruise.value, 1);
		}
		if ( Right(Div38.rdo_bruise.value, 1) == '3') {
			FV_EQP_E = 'Y';
		}
		if ( FV_EQP_ST < Right(Div38.rdo_bruise.value, 1) ) {
			FV_EQP_ST = Right(Div38.rdo_bruise.value, 1);
		}
		
		
		if ( FV_SALE_EQP_ST < Left(Div35.rdo_squash.value, 1) ) {
			FV_SALE_EQP_ST = Left(Div35.rdo_squash.value, 1);
		}
		if ( Right(Div35.rdo_squash.value, 1) == '3') {
			FV_EQP_E = 'Y';
		}
		if ( FV_EQP_ST < Right(Div35.rdo_squash.value, 1) ) {
			FV_EQP_ST = Right(Div35.rdo_squash.value, 1);
		}
		
		
		if ( FV_SALE_EQP_ST < Left(Div20.rdo_liquefied.value, 1) ) {
			FV_SALE_EQP_ST = Left(Div20.rdo_liquefied.value, 1);
		}
		if ( Right(Div20.rdo_liquefied.value, 1) == '3') {
			FV_EQP_E = 'Y';
		}
		if ( FV_EQP_ST < Right(Div20.rdo_liquefied.value, 1) ) {
			FV_EQP_ST = Right(Div20.rdo_liquefied.value, 1);
		}
		
		
		if ( FV_SALE_EQP_ST < Left(Div40.rdo_led.value, 1) ) {
			FV_SALE_EQP_ST = Left(Div40.rdo_led.value, 1);
		}
		if ( Right(Div40.rdo_led.value, 1) == '3') {
			FV_EQP_E = 'Y';
		}
		if ( FV_EQP_ST < Right(Div40.rdo_led.value, 1) ) {
			FV_EQP_ST = Right(Div40.rdo_led.value, 1);
		}
		
		
		if ( FV_SALE_EQP_ST < Left(Div11.rdo_button.value, 1) ) {
			FV_SALE_EQP_ST = Left(Div11.rdo_button.value, 1);
		}
		if ( Right(Div11.rdo_button.value, 1) == '3') {
			FV_EQP_E = 'Y';
		}
		if ( FV_EQP_ST < Right(Div11.rdo_button.value, 1) ) {
			FV_EQP_ST = Right(Div11.rdo_button.value, 1);
		}
		
		
		if ( FV_SALE_EQP_ST < Left(Div46.rdo_bottom.value, 1) ) {
			FV_SALE_EQP_ST = Left(Div46.rdo_bottom.value, 1);
		}
		if ( Right(Div46.rdo_bottom.value, 1) == '3') {
			FV_EQP_E = 'Y';
		}
		if ( FV_EQP_ST < Right(Div46.rdo_bottom.value, 1) ) {
			FV_EQP_ST = Right(Div46.rdo_bottom.value, 1);
		}
		
		
		if ( FV_SALE_EQP_ST < Left(Div43.rdo_body.value, 1) ) {
			FV_SALE_EQP_ST = Left(Div43.rdo_body.value, 1);
		}
		if ( Right(Div43.rdo_body.value, 1) == '3') {
			FV_EQP_E = 'Y';
		}
		if ( FV_EQP_ST < Right(Div43.rdo_body.value, 1) ) {
			FV_EQP_ST = Right(Div43.rdo_body.value, 1);
		}
		
		
		if ( FV_SALE_EQP_ST < Left(Div23.rdo_dmb.value, 1) ) {
			FV_SALE_EQP_ST = Left(Div23.rdo_dmb.value, 1);
		}
		if ( Right(Div23.rdo_dmb.value, 1) == '3') {
			FV_EQP_E = 'Y';
		}
		if ( FV_EQP_ST < Right(Div23.rdo_dmb.value, 1) ) {
			FV_EQP_ST = Right(Div23.rdo_dmb.value, 1);
		}

		
		if ( FV_SALE_EQP_ST < Left(Div47.rdo_glass.value, 1) ) {
			FV_SALE_EQP_ST = Left(Div47.rdo_glass.value, 1);
		}
		if ( Right(Div47.rdo_glass.value, 1) == '3') {
			FV_EQP_E = 'Y';
		}
		if ( FV_EQP_ST < Right(Div47.rdo_glass.value, 1) ) {
			FV_EQP_ST = Right(Div47.rdo_glass.value, 1);
		}
		
		
		if ( FV_SALE_EQP_ST < Left(Div26.rdo_teeth.value, 1) ) {
			FV_SALE_EQP_ST = Left(Div26.rdo_teeth.value, 1);
		}
		if ( Right(Div26.rdo_teeth.value, 1) == '3') {
			FV_EQP_E = 'Y';
		}
		if ( FV_EQP_ST < Right(Div26.rdo_teeth.value, 1) ) {
			FV_EQP_ST = Right(Div26.rdo_teeth.value, 1);
		}
		
		
		if ( FV_SALE_EQP_ST < Left(Div50.rdo_window.value, 1) ) {
			FV_SALE_EQP_ST = Left(Div50.rdo_window.value, 1);
		}
		if ( Right(Div50.rdo_window.value, 1) == '3') {
			FV_EQP_E = 'Y';
		}
		if ( FV_EQP_ST < Right(Div50.rdo_window.value, 1) ) {
			FV_EQP_ST = Right(Div50.rdo_window.value, 1);
		}
		
		
		if ( FV_SALE_EQP_ST < Left(Div37.rdo_edge.value, 1) ) {
			FV_SALE_EQP_ST = Left(Div37.rdo_edge.value, 1);
		}
		if ( Right(Div37.rdo_edge.value, 1) == '3') {
			FV_EQP_E = 'Y';
		}
		if ( FV_EQP_ST < Right(Div37.rdo_edge.value, 1) ) {
			FV_EQP_ST = Right(Div37.rdo_edge.value, 1);
		}	
			

		
				
		if (FV_SALE_EQP_ST == '1') {
			div_conInfo8.edt_saleEqpSt.Text = 'A+';
		}
		if (FV_SALE_EQP_ST == '2') {
			div_conInfo8.edt_saleEqpSt.Text = 'A0';
		}
		if (FV_SALE_EQP_ST == '3') {
			div_conInfo8.edt_saleEqpSt.Text = 'A-';
		}
		if (FV_SALE_EQP_ST == '4') {
			div_conInfo8.edt_saleEqpSt.Text = 'B';
		}
		if (FV_SALE_EQP_ST == '5') {
			div_conInfo8.edt_saleEqpSt.Text = 'E'; 
		}
		
		if (FV_EQP_ST == '1') {
			div_conInfo8.edt_eqpSt.Text = 'A';
		}
		if (FV_EQP_ST == '2') {
			div_conInfo8.edt_eqpSt.Text = 'B';
		}
		if (FV_EQP_ST == '3') {
			div_conInfo8.edt_eqpSt.Text = 'E';
		}
		
	}

}


/*******************************************************************************
 * @description    :  반송선택
*******************************************************************************/
function Div55_chk_returnYn_OnClick(obj,strValue)
{
	if(Div55.chk_returnYn.Value == "1") {
		div_conInfo8.edt_saleEqpSt.Text = '반송';
	} else {
		Div54.rdo_return.value = "";
		f_st_set();
	}	
}


/*******************************************************************************
 * @description    :  판매등급내역조회
*******************************************************************************/
function f_getSale_eqp()
{

	http.Sync = true;

	ds_saleEqpSt.ClearData();

    cf_setParam(ds_saleEqpSt, "CON_MGMT_NO" , FV_CON_MGMT_NO ); 

	var sSvcID 	= "getSaleEqp";
	var sInDs  	= "nc_input_fieldDs=ds_saleEqpSt";
	var sOutDs 	= "ds_saleEqpSt=ds_saleEqpSt";
alert("aaaaaa");	
	var sArg	= "sktst.cst.SKN#getSaleEqpC";
alert(sArg);	
	// 공통 트랜잭션 호출
	cf_Transaction(sSvcID, sInDs, sOutDs, sArg, null, true, true);

	http.Sync = false;		
	
}


/*******************************************************************************
 * @description    : 판매등급내역 저장
*******************************************************************************/
function btn_save_OnClick(obj)
{

	if ( !lf_saveValidationCheck() ) {
		return;
	}

	var sSvcID = "saveSaleEqpC";
	var sInDs  = "ds_saleEqpSt=ds_saleEqpSt";
	var sOutDs = "";
	var sArg   = "sktst.cst.SKN#saveSaleEqpC";

	cf_Transaction(sSvcID, sInDs, sOutDs, sArg);
//parent.f_saleEqpSt(div_conInfo8.edt_saleEqpSt.Text,div_conInfo8.edt_eqpSt.Text,FV_EQP_E);
//		this.Close();
		
	return;	
}


/*******************************************************************************
 * @description    :  callBack
*******************************************************************************/
function f_callBack(sSvcID)
{
	if (sSvcID == "getSaleEqp") {
		if (uf_IsNull(ds_saleEqpSt.GetColumn(0,"SEQ"))){
			ds_saleEqpSt.ClearData();
			cf_setParam(ds_saleEqpSt, "CON_MGMT_NO" , FV_CON_MGMT_NO ); 
		} else {
		}
    }else if (sSvcID == "saveSaleEqp") {
		alert("저장 되었습니다.);
		parent.f_saleEqpSt(div_conInfo8.edt_saleEqpSt.Text,div_conInfo8.edt_eqpSt.Text,FV_EQP_E);
		this.Close();
	}
}


/*******************************************************************************
 * @description    : 닫기버튼 클릭
*******************************************************************************/
function btn_close_OnClick(obj)
{

	this.close();
}


/*******************************************************************************
 * @description    :  판매등급등록 저장시 validation check
*******************************************************************************/
function lf_saveValidationCheck()
{

	var bFlag = true;

	if (uf_IsNull(div_choice1.rdo_power.value)){
		alert("기본점검 / 전원불량 을 선택하세요.");
		return false;
	}
	if (uf_IsNull(div_choice2.rdo_charge.value)){
		alert("기본점검 / 충전불량 을 선택하세요.");
		return false;
	}
	if (uf_IsNull(div_choice3.rdo_usim.value)){
		alert("기본점검 / USIM불량 을 선택하세요.");
		return false;
	}
	if (uf_IsNull(div_choice6.rdo_cpnt.value)){
		alert("구성품 없음을 선택하세요.");
		return false;
	}
	if (uf_IsNull(div_choice4.rdo_bell.value)){
		alert("기능점검 / 벨소리불량 을 선택하세요.");
		return false;
	}
	if (uf_IsNull(div_choice5.rdo_vibration.value)){
		alert("기능점검 / 진동불량 을 선택하세요.");
		return false;
	}
	if (uf_IsNull(div_choice7.rdo_jodo.value)){
		alert("기능점검 / 조도센서불량 을 선택하세요.");
		return false;
	}
	if (uf_IsNull(div_choice8.rdo_gyro.value)){
		alert("기능점검 / 자이로센서불량 을 선택하세요.");
		return false;
	}
	if (uf_IsNull(div_choice9.rdo_proximity.value)){
		alert("기능점검 / 근접센서불량 을 선택하세요.");
		return false;
	}
	if (uf_IsNull(div_choice10.rdo_camera.value)){
		alert("기능점검 / 카메라불량 을 선택하세요.");
		return false;
	}
	if (uf_IsNull(div_choice11.rdo_battery.value)){
		alert("기능점검 / BT불량 을 선택하세요.");
		return false;
	}
	if (uf_IsNull(div_choice12.rdo_afterimage.value)){
		alert("기능점검 / 잔상불량 을 선택하세요.");
		return false;
	}
	if (uf_IsNull(Div19.rdo_touch.value)){
		alert("기능점검 / 터치불량 을 선택하세요.");
		return false;
	}
	if (uf_IsNull(Div29.rdo_wifi.value)){
		alert("기능점검 / WIFI불량 을 선택하세요.");
		return false;
	}
    if (uf_IsNull(Div32.rdo_stain.value)){
		alert("화면점검 / 얼룩(흰색) 을 선택하세요.");
		return false;
	}
	if (uf_IsNull(Div38.rdo_bruise.value)){
		alert("화면점검 / 멍(자주색/오렌지색) 을 선택하세요.");
		return false;
	}
	if (uf_IsNull(Div35.rdo_squash.value)){
		alert("화면점검 / 눌림 을 선택하세요.");
		return false;
	}
	if (uf_IsNull(Div20.rdo_liquefied.value)){
		alert("화면점검 / 액상유입 을 선택하세요.");
		return false;
	}
	if (uf_IsNull(Div40.rdo_led.value)){
		alert("화면점검 / LED파손 을 선택하세요.");
		return false;
	}
	if (uf_IsNull(Div11.rdo_button.value)){
		alert("외관점검 / 버튼불량 을 선택하세요.");
		return false;
	}
	if (uf_IsNull(Div46.rdo_bottom.value)){
		alert("외관점검 / 하단터치메뉴불량 을 선택하세요.");
		return false;
	}
	if (uf_IsNull(Div43.rdo_body.value)){
		alert("외관점검 / 몸체 미세 휨 을 선택하세요.");
		return false;
	}
	if (uf_IsNull(Div23.rdo_dmb.value)){
		alert("외관점검 / DMB안테나 손상 을 선택하세요.");
		return false;
	}
	if (uf_IsNull(Div47.rdo_glass.value)){
		alert("외관점검 / 액정유리(터치판넬) 을 선택하세요.");
		return false;
	}
	if (uf_IsNull(Div26.rdo_teeth.value)){
		alert("외관점검 / 이나감 을 선택하세요.");
		return false;
	}
	if (uf_IsNull(Div50.rdo_window.value)){
		alert("외관점검 / 카메라 윈도우 손상 을 선택하세요.");
		return false;
	}	
	if (uf_IsNull(Div37.rdo_edge.value)){
		alert("외관점검 / 테두리 및 몸체 을 선택하세요.");
		return false;
	}	
	return bFlag;
}
]]></Script>
</Window>