<?xml version="1.0" encoding="utf-8"?>
<Window>
	<Form Height="500" Id="form" Left="8" OnLoadCompleted="form_OnLoadCompleted" PidAttrib="7" Title="단말기엑셀입력(SKN입고)" Top="8" Ver="1.0" Width="830" WorkArea="true">
		<Datasets>
			<Dataset DataSetType="Dataset" Id="ds_upLoadXlsList">
				<Contents>
					<colinfo id="NO" size="256" summ="default" type="STRING"/>
					<colinfo id="PROD_CD" size="256" summ="default" type="STRING"/>
					<colinfo id="SER_NUM" size="256" summ="default" type="STRING"/>
					<colinfo id="CON_DT" size="256" summ="default" type="STRING"/>
					<colinfo id="CON_PLC_CD" size="256" summ="default" type="STRING"/>
					<colinfo id="SVC_DT" size="256" summ="default" type="STRING"/>
					<colinfo id="EQP_ST" size="256" summ="default" type="STRING"/>
					<colinfo id="COLOR_CD" size="256" summ="default" type="STRING"/>
					<colinfo id="LOST_YN" size="256" summ="default" type="STRING"/>
					<colinfo id="RETURN_YN" size="256" summ="default" type="STRING"/>
					<colinfo id="LEASE_YN" size="256" summ="default" type="STRING"/>
					<colinfo id="USIM_YN" size="256" summ="default" type="STRING"/>
					<colinfo id="OTHER_YN" size="256" summ="default" type="STRING"/>
					<colinfo id="SVC_NO" size="256" summ="default" type="STRING"/>
					<colinfo id="SVC_MGMT_NO" size="256" summ="default" type="STRING"/>
					<colinfo id="IMEI" size="256" summ="default" type="STRING"/>
					<colinfo id="CHAG_DEDT_YN" size="256" summ="default" type="STRING"/>
					<colinfo id="PRCHS_AMT" size="256" summ="default" type="STRING"/>
					<colinfo id="BUY_CL" size="256" summ="default" type="STRING"/>
					<colinfo id="CHECK_DT" size="256" summ="default" type="STRING"/>
					<colinfo id="CUST_YN" size="256" summ="default" type="STRING"/>
					<colinfo id="CUST_DT" size="256" summ="default" type="STRING"/>
					<colinfo id="RES_NO" size="256" summ="default" type="STRING"/>
					<colinfo id="CUST_NM" size="256" summ="default" type="STRING"/>
					<colinfo id="BANK_CD" size="256" summ="default" type="STRING"/>
					<colinfo id="ACC_NO" size="256" summ="default" type="STRING"/>
					<colinfo id="TEL_NO" size="256" summ="default" type="STRING"/>
					<colinfo id="ZIP_CD1" size="256" summ="default" type="STRING"/>
					<colinfo id="ZIP_CD2" size="256" summ="default" type="STRING"/>
					<colinfo id="ADDR" size="256" summ="default" type="STRING"/>
					<colinfo id="DTL_ADDR" size="256" summ="default" type="STRING"/>
					<colinfo id="RMKS" size="256" summ="default" type="STRING"/>
					<colinfo id="T_MGMT_NO" size="256" summ="default" type="STRING"/>
					<colinfo id="BATTERY" size="256" summ="default" type="STRING"/>
					<colinfo id="CHARGER" size="256" summ="default" type="STRING"/>
					<colinfo id="ZENDER" size="256" summ="default" type="STRING"/>
					<colinfo id="EARPHONES" size="256" summ="default" type="STRING"/>
					<colinfo id="CASE" size="256" summ="default" type="STRING"/>
					<colinfo id="USB" size="256" summ="default" type="STRING"/>
					<colinfo id="MEMORY" size="256" summ="default" type="STRING"/>
					<colinfo id="DTL_1" size="256" summ="default" type="STRING"/>
					<colinfo id="DTL_2" size="256" summ="default" type="STRING"/>
					<colinfo id="DTL_3" size="256" summ="default" type="STRING"/>
					<colinfo id="OTHER" size="256" summ="default" type="STRING"/>
					<colinfo id="ERR_DESC" size="256" summ="default" type="STRING"/>
					<colinfo id="CON_MGMT_NO" size="256" summ="default" type="STRING"/>
					<colinfo id="PRCHS_MGMT_NO" size="256" summ="default" type="STRING"/>
					<colinfo id="PROD_NM" size="256" summ="default" type="STRING"/>
					<colinfo id="CON_PLC_NM" size="256" summ="default" type="STRING"/>
					<colinfo id="BANK_NM" size="256" summ="default" type="STRING"/>
					<colinfo id="ACC_NM" size="256" summ="default" type="STRING"/>
				</Contents>
			</Dataset>
			<Dataset DataSetType="Dataset" Id="ds_prodList">
				<Contents>
					<colinfo id="prodCd" size="256" summ="default" type="STRING"/>
					<colinfo id="prodCnt" size="256" summ="default" type="STRING"/>
				</Contents>
			</Dataset>
			<Dataset DataSetType="Dataset" Id="ds_inoutCl">
				<Contents>
					<colinfo id="inout_cl" size="256" summ="default" type="STRING"/>
				</Contents>
			</Dataset>
		</Datasets>
		<Div Border="Raised" Height="40" Id="div_Search" Left="10" Style="sty_div_input" TabOrder="5" Text="Div0" Top="35" Width="810">
			<Contents>
				<Static Align="Right" Border="None" Height="20" Id="Static0" Left="4" Style="sty_lb_Basic" TabOrder="2" Text="파일선택" Top="7" VAlign="Middle" Width="84"></Static>
				<Edit Border="Flat" Height="20" Id="edt_filePath" Left="89" LeftMargin="2" RightMargin="2" Style="sty_ipt_form" TabOrder="3" Top="7" Width="440"></Edit>
				<Button Cursor="HAND" Height="20" Id="btn_search" ImageID="btn_i_detail_b" Left="529" OnClick="btn_search_OnClick" TabOrder="3" Text="Button0" Top="7" Width="20"></Button>
				<Button Align="Left" ButtonStyle="TRUE" Cursor="HAND" Height="21" Id="btn_errCheck" ImageID="btn_a_4" Left="558" LeftMargin="5" OnClick="btn_errCheck_OnClick" Style="sty_btn_a" TabOrder="1" Text="오류검증" Top="7" Width="85"></Button>
				<Button Align="Left" ButtonStyle="TRUE" Cursor="HAND" Height="21" Id="btn_excelSave" ImageID="btn_a_4" Left="648" LeftMargin="5" OnClick="btn_excelSave_OnClick" Style="sty_btn_a" TabOrder="3" Text="엑셀반영" Top="7" Width="85"></Button>
				<FileDialog Bottom="29" Filter="Excel&#32;Files&#32;(*.xls;*.xlsx)|*.xls;*.xlsx" Height="24" Id="fld_excel" Left="772" Right="796" TabOrder="7" Top="5" Type="Save" Width="24"></FileDialog>
			</Contents>
		</Div>
		<Grid BindDataset="ds_upLoadXlsList" BkColor2="user32" BoldHead="true" Border="Flat" Bottom="463" Enable="true" EndLineColor="default" FillArea="TRUE" HeadBorder="Flat" HeadHeight="20" Height="359" Id="grd_upLoadXlsList" InputPanel="FALSE" Left="8" LineColor="user33" Right="818" RowHeight="20" Style="sty_Grid" TabOrder="-1" TabStop="true" Top="104" UseDBuff="true" UsePopupMenu="true" UseSelColor="true" Visible="true" VLineColor="user33" WheelScrollRow="1" Width="810">
			<contents>
				<format id="Default">
					<columns>
						<col width="32"/>
						<col width="70"/>
						<col width="90"/>
						<col width="75"/>
						<col width="75"/>
						<col width="85"/>
						<col width="70"/>
						<col width="120"/>
						<col width="80"/>
						<col width="75"/>
						<col width="75"/>
						<col width="100"/>
						<col width="110"/>
						<col width="75"/>
						<col width="95"/>
						<col width="130"/>
						<col width="85"/>
						<col width="95"/>
						<col width="85"/>
						<col width="80"/>
						<col width="90"/>
						<col width="60"/>
						<col width="65"/>
						<col width="60"/>
						<col width="85"/>
						<col width="80"/>
						<col width="60"/>
						<col width="55"/>
						<col width="80"/>
						<col width="85"/>
						<col width="85"/>
						<col width="65"/>
						<col width="70"/>
						<col width="270"/>
						<col width="310"/>
						<col width="255"/>
						<col width="75"/>
						<col width="55"/>
						<col width="55"/>
						<col width="55"/>
						<col width="55"/>
						<col width="70"/>
						<col width="85"/>
						<col width="75"/>
						<col width="60"/>
						<col width="65"/>
						<col width="65"/>
						<col width="185"/>
						<col width="100"/>
						<col width="60"/>
						<col width="100"/>
					</columns>
					<head>
						<cell align="center" bkcolor="user34" col="0" color="user35" display="text" font="돋움,9,Bold" text="No" Valign="Center"/>
						<cell align="center" bkcolor="user34" col="1" color="user35" display="text" font="돋움,9,Bold" text="모델코드" Valign="Center"/>
						<cell align="center" bkcolor="user34" col="2" color="user35" display="text" font="돋움,9,Bold" text="모델명" Valign="Center"/>
						<cell align="center" bkcolor="user34" col="3" color="user35" display="text" font="돋움,9,Bold" text="일련번호" Valign="Center"/>
						<cell align="center" bkcolor="user34" col="4" color="user35" display="text" font="돋움,9,Bold" text="고객명" Valign="Center"/>
						<cell align="center" bkcolor="user34" col="5" color="user35" display="text" font="돋움,9,Bold" text="상담일자" Valign="Center"/>
						<cell align="center" bkcolor="user34" col="6" color="user35" display="text" font="돋움,9,Bold" text="상담처코드" Valign="Center"/>
						<cell align="center" bkcolor="user34" col="7" color="user35" display="text" font="돋움,9,Bold" text="상담처명" Valign="Center"/>
						<cell align="center" bkcolor="user34" col="8" color="user35" display="text" font="돋움,9,Bold" text="개통일자" Valign="Center"/>
						<cell align="center" bkcolor="user34" col="9" color="user35" display="text" font="돋움,9,Bold" text="단말기등급" Valign="Center"/>
						<cell align="center" bkcolor="user34" col="10" color="user35" display="text" font="돋움,9,Bold" text="색상" Valign="Center"/>
						<cell align="center" bkcolor="user34" col="11" color="user35" display="text" font="돋움,9,Bold" text="분실단말기여부" Valign="Center"/>
						<cell align="center" bkcolor="user34" col="12" color="user35" display="text" font="돋움,9,Bold" text="보상반납대상여부" Valign="Center"/>
						<cell align="center" bkcolor="user34" col="13" color="user35" display="text" font="돋움,9,Bold" text="임대폰여부" Valign="Center"/>
						<cell align="center" bkcolor="user34" col="14" color="user35" display="text" font="돋움,9,Bold" text="USIM기변여부" Valign="Center"/>
						<cell align="center" bkcolor="user34" col="15" color="user35" display="text" font="돋움,9,Bold" text="타사/해외단말기여부" Valign="Center"/>
						<cell align="center" bkcolor="user34" col="16" color="user35" display="text" font="돋움,9,Bold" text="서비스번호" Valign="Center"/>
						<cell align="center" bkcolor="user34" col="17" color="user35" display="text" font="돋움,9,Bold" text="서비스관리번호" Valign="Center"/>
						<cell align="center" bkcolor="user34" col="18" color="user35" display="text" font="돋움,9,Bold" text="IMEI" Valign="Center"/>
						<cell align="center" bkcolor="user34" col="19" color="user35" display="text" font="돋움,9,Bold" text="요금공제여부" Valign="Center"/>
						<cell align="center" bkcolor="user34" col="20" color="user35" display="text" font="돋움,9,Bold" text="매입금액" Valign="Center"/>
						<cell align="center" bkcolor="user34" col="21" color="user35" display="text" font="돋움,9,Bold" text="검수구분" Valign="Center"/>
						<cell align="center" bkcolor="user34" col="22" color="user35" display="text" font="돋움,9,Bold" text="검수일자" Valign="Center"/>
						<cell align="center" bkcolor="user34" col="23" color="user35" display="text" font="돋움,9,Bold" text="고객의사" Valign="Center"/>
						<cell align="center" bkcolor="user34" col="24" color="user35" display="text" font="돋움,9,Bold" text="고객확인일자" Valign="Center"/>
						<cell align="center" bkcolor="user34" col="25" color="user35" display="text" font="돋움,9,Bold" text="주민번호" Valign="Center"/>
						<cell align="center" bkcolor="user34" col="26" color="user35" display="text" font="돋움,9,Bold" text="예금주" Valign="Center"/>
						<cell align="center" bkcolor="user34" col="27" color="user35" display="text" font="돋움,9,Bold" text="은행코드" Valign="Center"/>
						<cell align="center" bkcolor="user34" col="28" color="user35" display="text" font="돋움,9,Bold" text="은행명" Valign="Center"/>
						<cell align="center" bkcolor="user34" col="29" color="user35" display="text" font="돋움,9,Bold" text="계좌번호" Valign="Center"/>
						<cell align="center" bkcolor="user34" col="30" color="user35" display="text" font="돋움,9,Bold" text="전화번호" Valign="Center"/>
						<cell align="center" bkcolor="user34" col="31" color="user35" display="text" font="돋움,9,Bold" text="우편번호1" Valign="Center"/>
						<cell align="center" bkcolor="user34" col="32" color="user35" display="text" font="돋움,9,Bold" text="우편번호2" Valign="Center"/>
						<cell align="center" bkcolor="user34" col="33" color="user35" display="text" font="돋움,9,Bold" text="주소" Valign="Center"/>
						<cell align="center" bkcolor="user34" col="34" color="user35" display="text" font="돋움,9,Bold" text="기타주소" Valign="Center"/>
						<cell align="center" bkcolor="user34" col="35" color="user35" display="text" font="돋움,9,Bold" text="의견" Valign="Center"/>
						<cell align="center" bkcolor="user34" col="36" color="user35" display="text" font="돋움,9,Bold" text="T_관리번호" Valign="Center"/>
						<cell align="center" bkcolor="user34" col="37" color="user35" display="text" font="돋움,9,Bold" text="배터리" Valign="Center"/>
						<cell align="center" bkcolor="user34" col="38" color="user35" display="text" font="돋움,9,Bold" text="충전기" Valign="Center"/>
						<cell align="center" bkcolor="user34" col="39" color="user35" display="text" font="돋움,9,Bold" text="젠더" Valign="Center"/>
						<cell align="center" bkcolor="user34" col="40" color="user35" display="text" font="돋움,9,Bold" text="이어폰" Valign="Center"/>
						<cell align="center" bkcolor="user34" col="41" color="user35" display="text" font="돋움,9,Bold" text="충전&#32;Case" Valign="Center"/>
						<cell align="center" bkcolor="user34" col="42" color="user35" display="text" font="돋움,9,Bold" text="USB&#32;CABLE" Valign="Center"/>
						<cell align="center" bkcolor="user34" col="43" color="user35" display="text" font="돋움,9,Bold" text="메모리카드" Valign="Center"/>
						<cell align="center" bkcolor="user34" col="44" color="user35" display="text" font="돋움,9,Bold" text="구성품_1" Valign="Center"/>
						<cell align="center" bkcolor="user34" col="45" color="user35" display="text" font="돋움,9,Bold" text="구성품_2" Valign="Center"/>
						<cell align="center" bkcolor="user34" col="46" color="user35" display="text" font="돋움,9,Bold" text="구성품_3" Valign="Center"/>
						<cell align="center" bkcolor="user34" col="47" color="user35" display="text" font="돋움,9,Bold" text="기타구성품" Valign="Center"/>
						<cell align="center" bkcolor="user34" col="48" color="user35" display="text" font="돋움,9,Bold" text="단체명" Valign="Center"/>
						<cell align="center" bkcolor="user34" col="49" color="user35" display="text" font="돋움,9,Bold" text="처리구분" Valign="Center"/>
						<cell align="center" bkcolor="user34" col="50" color="user35" display="text" font="돋움,9,Bold" text="ERROR" Valign="Center"/>
					</head>
					<body>
						<cell align="center" bkcolor2="user36" col="0" display="text" expr="currow+1"/>
						<cell align="center" bkcolor2="user36" col="1" colid="PROD_CD" display="text"/>
						<cell align="left" bkcolor2="user36" col="2" colid="PROD_NM" display="text"/>
						<cell align="center" bkcolor2="user36" col="3" colid="SER_NUM" display="text"/>
						<cell align="center" bkcolor2="user36" col="4" colid="CUST_NM" display="text"/>
						<cell align="center" bkcolor2="user36" col="5" colid="CON_DT" display="date"/>
						<cell align="center" bkcolor2="user36" col="6" colid="CON_PLC_CD" display="text"/>
						<cell align="left" bkcolor2="user36" col="7" colid="CON_PLC_NM" display="text"/>
						<cell align="center" bkcolor2="user32" col="8" colid="SVC_DT" display="date"/>
						<cell align="center" bkcolor2="user32" col="9" colid="EQP_ST" display="text"/>
						<cell align="center" bkcolor2="user32" col="10" colid="COLOR_CD" display="text"/>
						<cell align="center" bkcolor2="user32" col="11" colid="LOST_YN" display="text"/>
						<cell align="center" bkcolor2="user32" col="12" colid="RETURN_YN" display="text"/>
						<cell align="center" bkcolor2="user32" col="13" colid="LEASE_YN" display="text"/>
						<cell align="center" bkcolor2="user32" col="14" colid="USIM_YN" display="text"/>
						<cell align="center" bkcolor2="user32" col="15" colid="OTHER_YN" display="text"/>
						<cell align="center" bkcolor2="user32" col="16" colid="SVC_NO" display="text"/>
						<cell align="center" bkcolor2="user32" col="17" colid="SVC_MGMT_NO" display="text"/>
						<cell align="center" bkcolor2="user32" col="18" colid="IMEI" display="text"/>
						<cell align="center" bkcolor2="user32" col="19" colid="CHAG_DEDT_YN" display="text"/>
						<cell align="right" bkcolor2="user32" col="20" colid="PRCHS_AMT" display="number"/>
						<cell align="center" bkcolor2="user32" col="21" colid="BUY_CL" display="text"/>
						<cell align="center" bkcolor2="user32" col="22" colid="CHECK_DT" display="date"/>
						<cell align="center" bkcolor2="user32" col="23" colid="CUST_YN" display="text"/>
						<cell align="center" bkcolor2="user32" col="24" colid="CUST_DT" display="date"/>
						<cell align="center" bkcolor2="user32" col="25" colid="RES_NO" display="text"/>
						<cell align="center" bkcolor2="user32" col="26" colid="ACC_NM" display="text"/>
						<cell align="center" bkcolor2="user32" col="27" colid="BANK_CD" display="text"/>
						<cell align="center" bkcolor2="user32" col="28" colid="BANK_NM" display="text"/>
						<cell align="center" bkcolor2="user32" col="29" colid="ACC_NO" display="text"/>
						<cell align="center" bkcolor2="user32" col="30" colid="TEL_NO" display="text"/>
						<cell align="center" bkcolor2="user32" col="31" colid="ZIP_CD1" display="text"/>
						<cell align="center" bkcolor2="user32" col="32" colid="ZIP_CD2" display="text"/>
						<cell align="left" bkcolor2="user32" col="33" colid="ADDR" display="text"/>
						<cell align="left" bkcolor2="user32" col="34" colid="DTL_ADDR" display="text"/>
						<cell align="left" bkcolor2="user32" col="35" colid="RMKS" display="text"/>
						<cell align="center" bkcolor2="user32" col="36" colid="T_MGMT_NO" display="text"/>
						<cell align="center" bkcolor2="user32" col="37" colid="BATTERY" display="text"/>
						<cell align="center" bkcolor2="user32" col="38" colid="CHARGER" display="text"/>
						<cell align="center" bkcolor2="user32" col="39" colid="ZENDER" display="text"/>
						<cell align="center" bkcolor2="user32" col="40" colid="EARPHONES" display="text"/>
						<cell align="center" bkcolor2="user32" col="41" colid="CASE" display="text"/>
						<cell align="center" bkcolor2="user32" col="42" colid="USB" display="text"/>
						<cell align="center" bkcolor2="user32" col="43" colid="MEMORY" display="text"/>
						<cell align="center" bkcolor2="user32" col="44" colid="DTL_1" display="text"/>
						<cell align="center" bkcolor2="user32" col="45" colid="DTL_2" display="text"/>
						<cell align="center" bkcolor2="user32" col="46" colid="DTL_3" display="text"/>
						<cell align="center" bkcolor2="user32" col="47" colid="OTHER" display="text"/>
						<cell align="left" bkcolor2="user32" col="48" colid="CUST_GROUP_NM" display="text"/>
						<cell align="center" bkcolor2="user32" col="49" colid="PRC_GB" display="text"/>
						<cell align="left" bkcolor2="user32" col="50" colid="ERR_DESC" display="text"/>
					</body>
				</format>
			</contents>
		</Grid>
		<Button Cursor="HAND" Height="20" Id="btn_delRow" ImageID="btn_i_subtract_w" Left="801" OnClick="btn_delRow_OnClick" TabOrder="0" Text="Button7" Top="81" Width="20"></Button>
		<Image Align="Left" Height="25" Id="Image0" ImageID="bul_tit" Left="10" LeftMargin="15" Style="sty_img_tit" TabOrder="4" Text="엑셀입력" Top="10" Width="192"></Image>
		<Button Align="Left" ButtonStyle="TRUE" Height="24" Id="btn_close" ImageID="btn_d_2" Left="762" LeftMargin="5" OnClick="btn_close_OnClick" Style="sty_btn_d" TabOrder="5" Text="닫기" Top="468" Width="61"></Button>
		<Static Border="None" Height="20" Id="Static1" Left="24" Style="sty_lb_Search" TabOrder="6" Text="처리구분&#32;:&#32;C(일반감정)&#32;,&#32;T(T&#32;SMART),&#32;N(현장감정),&#32;UC(4U일반감정),&#32;UN(4U현장감정)" Top="80" VAlign="Middle" Width="744"></Static>
	</Form>
	<Script><![CDATA[/*******************************************************************************
* 프로그램ID  : CSTADVO00810
* 업무명      : 상담
* 프로그램명  : 단말기엑셀입력(입고)
--------------------------------------------------------------------------------
* 작성자      : 민동운
* 작성일      : 2012.02.23
--------------------------------------------------------------------------------
* 1. 변경이력
수정자    :
수정일    :
수정 내역 :
*******************************************************************************/

//==============================================================================
// 공통 스크립트 로딩
//==============================================================================
#include "lib::lib_commF.js"
#include "lib::lib_commMsg.js"

//==============================================================================
// 폼 변수 정의
//==============================================================================
var FV_INOUT_CL; //입고구분

/*******************************************************************************
 * @description    : 최초 폼 로드시 발생 - 이벤트
*******************************************************************************/
function form_OnLoadCompleted(obj)
{
	//엑셀반영 버튼 
	div_Search.btn_excelSave.Enable = false;
}

/*******************************************************************************
 * @description    : 콜백
 * @param sSvcID   : 서비스 아이디
*******************************************************************************/
function f_callBack(sSvcID)
{	
	if(sSvcId == 'errCheck'){
	
		if(ds_upLoadXlsList.GetRowCount() == 0) return;
		
		var sOldValue = '';
		var sNewValue = '';		

		ds_upLoadXlsList.Sort("order_key");

		//동일 모델, 색상중 중복된 일련번호가 있는지 확인한다.
		for(var i = 0 ; i < ds_upLoadXlsList.GetRowCount() ; i++ ){		
			
			if(i != 0 ){

				if( !uf_IsNull(ds_upLoadXlsList.GetColumn(i,"order_key"))
					&& ds_upLoadXlsList.GetColumn(i-1,"order_key") 
					== ds_upLoadXlsList.GetColumn(i,"order_key")){					
				
					//번째 라인의 상품과 일련번호 중복입니다.
					ds_upLoadXlsList.SetColumn(i,"err_desc",cf_getMessage(MSG_00105, i+""));
				}
			}
		}	
		
		//엑셀반영 버튼 활성화.
		div_Search.btn_excelSave.Enable = true;

	}
	
	if(sSvcId == 'saveConsultMgmtXlsIn'){
		alert("엑셀업로드가 완료 되었습니다.");
		this.Close();
	}

}
/*******************************************************************************
 공통 스크립트 영역 끝
*******************************************************************************/

/*******************************************************************************
 * @description    : 엑셀업로드 - 이벤트
*******************************************************************************/
function btn_search_OnClick(obj)
{
	//엑셀반영 버튼 비활성화.
	div_Search.btn_excelSave.Enable = false;

    //데이터셋 초기화 및 컬럼 재정의
	ds_upLoadXlsList.Clear();
	cf_setParam(ds_upLoadXlsList, "NO", "");
	cf_setParam(ds_upLoadXlsList, "PROD_CD", "");
	cf_setParam(ds_upLoadXlsList, "PROD_NM", "");
	cf_setParam(ds_upLoadXlsList, "SER_NUM", "");
	cf_setParam(ds_upLoadXlsList, "CUST_NM", "");
	cf_setParam(ds_upLoadXlsList, "CON_DT", "");
	cf_setParam(ds_upLoadXlsList, "CON_PLC_CD", "");
	cf_setParam(ds_upLoadXlsList, "CON_PLC_NM", "");
	cf_setParam(ds_upLoadXlsList, "SVC_DT", "");
	cf_setParam(ds_upLoadXlsList, "EQP_ST", "");
	cf_setParam(ds_upLoadXlsList, "COLOR_CD", "");
	cf_setParam(ds_upLoadXlsList, "LOST_YN", "");
	cf_setParam(ds_upLoadXlsList, "RETURN_YN", "");
	cf_setParam(ds_upLoadXlsList, "LEASE_YN", "");
	cf_setParam(ds_upLoadXlsList, "USIM_YN", "");
	cf_setParam(ds_upLoadXlsList, "OTHER_YN", "");
	cf_setParam(ds_upLoadXlsList, "SVC_NO", "");
	cf_setParam(ds_upLoadXlsList, "SVC_MGMT_NO", "");
	cf_setParam(ds_upLoadXlsList, "IMEI", "");
	cf_setParam(ds_upLoadXlsList, "CHAG_DEDT_YN", "");
	cf_setParam(ds_upLoadXlsList, "PRCHS_AMT", "");
	cf_setParam(ds_upLoadXlsList, "BUY_CL", "");
	cf_setParam(ds_upLoadXlsList, "CHECK_DT", "");
	cf_setParam(ds_upLoadXlsList, "CUST_YN", "");
	cf_setParam(ds_upLoadXlsList, "CUST_DT", "");
	cf_setParam(ds_upLoadXlsList, "RES_NO", "");
	cf_setParam(ds_upLoadXlsList, "ACC_NM", "");
	cf_setParam(ds_upLoadXlsList, "BANK_CD", "");
	cf_setParam(ds_upLoadXlsList, "BANK_NM", "");
	cf_setParam(ds_upLoadXlsList, "ACC_NO", "");
	cf_setParam(ds_upLoadXlsList, "TEL_NO", "");
	cf_setParam(ds_upLoadXlsList, "ZIP_CD1", "");
	cf_setParam(ds_upLoadXlsList, "ZIP_CD2", "");
	cf_setParam(ds_upLoadXlsList, "ADDR", "");
	cf_setParam(ds_upLoadXlsList, "DTL_ADDR", "");
	cf_setParam(ds_upLoadXlsList, "RMKS", "");
	cf_setParam(ds_upLoadXlsList, "T_MGMT_NO", "");
	cf_setParam(ds_upLoadXlsList, "BATTERY", "");
	cf_setParam(ds_upLoadXlsList, "CHARGER", "");
	cf_setParam(ds_upLoadXlsList, "ZENDER", "");
	cf_setParam(ds_upLoadXlsList, "EARPHONES", "");
	cf_setParam(ds_upLoadXlsList, "CASE", "");
	cf_setParam(ds_upLoadXlsList, "USB", "");
	cf_setParam(ds_upLoadXlsList, "MEMORY", "");
	cf_setParam(ds_upLoadXlsList, "DTL_1", "");
	cf_setParam(ds_upLoadXlsList, "DTL_2", "");
	cf_setParam(ds_upLoadXlsList, "DTL_3", "");
	cf_setParam(ds_upLoadXlsList, "OTHER", "");
	cf_setParam(ds_upLoadXlsList, "CUST_GROUP_NM", "");
	cf_setParam(ds_upLoadXlsList, "PRC_GB", "");
	cf_setParam(ds_upLoadXlsList, "ERR_DESC", "");	

	var	sDsName = "ds_upLoadXlsList"; //데이터셋
	var	nUseDsInfo = 1;	              //기본정보
	var	nStartIndex = 2;              //시작index

	div_Search.fld_excel.Type = "OPEN";
	var bResult = div_Search.fld_excel.Open();
	
	if ( bResult )
	{
		var sFullPath = div_Search.fld_excel.FilePath + '\\' + div_Search.fld_excel.FileName;
		div_Search.edt_filePath.Text = sFullPath;

		return ext_ExcelImportByIndex(sFullPath, 0, sDsName, nUseDsInfo, 0, 0, nStartIndex);
	}	
}

/*******************************************************************************
 * @description    : 로우 삭제- 이벤트
*******************************************************************************/
function btn_delRow_OnClick(obj)
{
	var oGrdDs = object(grd_upLoadXlsList.BindDataset);
	oGrdDs.DeleteRow(oGrdDs.row);
}

/*******************************************************************************
 * @description    : 오류검증- 이벤트
*******************************************************************************/
function btn_errCheck_OnClick(obj)
{ 
	if(ds_upLoadXlsList.GetRowCount() == 0 
		|| (ds_upLoadXlsList.GetRowCount() == 1 && uf_IsNull(ds_upLoadXlsList.GetColumn(0,"prod_nm")) ) ){
		//업로드 문서에 처리 할 데이터가 없습니다.\n업로드 문서를 확인하시기 바랍니다.
		alert(MSG_00106);
		return;
	}	

	for(var i = 0 ; i < ds_upLoadXlsList.rowcount ; i++) {
		if (uf_IsNull(ds_upLoadXlsList.GetColumn(i,"PROD_CD")) ||
			uf_IsNull(ds_upLoadXlsList.GetColumn(i,"SER_NUM")) ||
			uf_IsNull(ds_upLoadXlsList.GetColumn(i,"PRC_GB")) ||
			(ds_upLoadXlsList.GetColumn(i,"PRC_GB") == 'T' || ds_upLoadXlsList.GetColumn(i,"PRC_GB") == 'UC' ||
			 ds_upLoadXlsList.GetColumn(i,"PRC_GB") == 'UN') &&	uf_IsNull(ds_upLoadXlsList.GetColumn(i,"T_MGMT_NO"))) {
			ds_upLoadXlsList.SetColumn(i, "ERR_DESC", "필수항목 공백 오류");
		}
		ds_upLoadXlsList.SetColumn(i, "CON_DT", ds_upLoadXlsList.GetColumn(i,"CON_DT").replace("-",""));
		ds_upLoadXlsList.SetColumn(i, "SVC_DT", ds_upLoadXlsList.GetColumn(i,"SVC_DT").replace("-",""));
		ds_upLoadXlsList.SetColumn(i, "CHECK_DT", ds_upLoadXlsList.GetColumn(i,"CHECK_DT").replace("-",""));
		ds_upLoadXlsList.SetColumn(i, "CUST_DT", ds_upLoadXlsList.GetColumn(i,"CUST_DT").replace("-",""));
		ds_upLoadXlsList.SetColumn(i, "TEL_NO", ds_upLoadXlsList.GetColumn(i,"TEL_NO").replace("-",""));
	}
	
	

	//엑셀반영 버튼 활성화.
	div_Search.btn_excelSave.Enable = true;


}

/*******************************************************************************
 * @description    : 엑셀반영- 이벤트
*******************************************************************************/
function btn_excelSave_OnClick(obj)
{	
	var icnt = 0;
	
	for(var i = ds_upLoadXlsList.GetRowCount()-1 ; i >= 0 ; i-- ){
	
		if(ds_upLoadXlsList.GetColumn(i,"ERR_DESC") != '' && ds_upLoadXlsList.GetColumn(i,"err_desc") != null ){
			icnt++;
		}
	}

	if(icnt > 0){
		if(!confirm("오류사항이 발생된 모델은 업로드 시 자동 제외 합니다. \n계속 하시겠습니까?")){
			return;
		}
	}
	
	//오류건 삭제하기.
	for(var i = ds_upLoadXlsList.GetRowCount()-1 ; i >= 0 ; i-- ){
		if(ds_upLoadXlsList.GetColumn(i,"err_desc") != '' && ds_upLoadXlsList.GetColumn(i,"err_desc") != null ){
			ds_upLoadXlsList.DeleteRow(i);
		}
	}
	
	if(ds_upLoadXlsList.GetRowCount() == 0 ){
		alert(MSG_00117);
		return;
	}
	
//trace(ds_upLoadXlsList.SaveXML()); 

 	var sSvcID = "saveConsultMgmtXlsIn";
	var sInDs  = "ds_upLoadXlsList=ds_upLoadXlsList";
	var sOutDs = "";
	var sArg   = "sktst.cst.SKN#saveConsultMgmtSknXlsIn";

	cf_Transaction(sSvcID, sInDs, sOutDs, sArg);

//	this.Close();
}


function btn_close_OnClick(obj)
{
	this.close();	
}

]]></Script>
</Window>